[{"lo":117.301,"la":-7.558,"de":305.2,"mw":5.8,"yr":1996,"ft":"T","s1":199,"d1":21,"r1":66,"s2":45,"d2":71,"r2":99,"label":""},{"lo":120.098,"la":1.028,"de":18.0,"mw":5.8,"yr":1996,"ft":"T","s1":52,"d1":17,"r1":66,"s2":257,"d2":74,"r2":97,"label":""},{"lo":120.406,"la":1.023,"de":15.0,"mw":5.6,"yr":1996,"ft":"T","s1":32,"d1":4,"r1":34,"s2":267,"d2":88,"r2":93,"label":""},{"lo":120.407,"la":1.112,"de":41.9,"mw":5.5,"yr":1996,"ft":"T","s1":58,"d1":22,"r1":66,"s2":264,"d2":70,"r2":100,"label":""},{"lo":120.453,"la":0.36,"de":24.2,"mw":5.7,"yr":1996,"ft":"N","s1":46,"d1":29,"r1":-67,"s2":200,"d2":63,"r2":-102,"label":""},{"lo":122.564,"la":1.37,"de":27.3,"mw":5.7,"yr":1996,"ft":"T","s1":87,"d1":21,"r1":58,"s2":301,"d2":72,"r2":102,"label":""},{"lo":122.795,"la":-0.006,"de":177.6,"mw":5.8,"yr":1996,"ft":"S","s1":285,"d1":45,"r1":131,"s2":54,"d2":58,"r2":57,"label":""},{"lo":122.939,"la":-0.018,"de":133.3,"mw":5.6,"yr":1996,"ft":"S","s1":289,"d1":54,"r1":135,"s2":50,"d2":55,"r2":46,"label":""},{"lo":124.622,"la":-2.099,"de":24.8,"mw":5.5,"yr":1996,"ft":"S","s1":297,"d1":62,"r1":3,"s2":205,"d2":87,"r2":152,"label":""},{"lo":125.017,"la":-0.239,"de":57.1,"mw":5.7,"yr":1996,"ft":"S","s1":145,"d1":50,"r1":-47,"s2":270,"d2":56,"r2":-129,"label":""},{"lo":125.144,"la":-0.071,"de":15.0,"mw":5.9,"yr":1996,"ft":"T","s1":235,"d1":18,"r1":123,"s2":20,"d2":75,"r2":80,"label":""},{"lo":125.167,"la":2.798,"de":152.7,"mw":5.9,"yr":1996,"ft":"N","s1":160,"d1":35,"r1":-145,"s2":40,"d2":71,"r2":-60,"label":""},{"lo":125.201,"la":-0.274,"de":42.4,"mw":5.5,"yr":1996,"ft":"T","s1":234,"d1":28,"r1":92,"s2":52,"d2":62,"r2":89,"label":""},{"lo":126.218,"la":3.098,"de":37.6,"mw":5.6,"yr":1996,"ft":"T","s1":30,"d1":26,"r1":80,"s2":221,"d2":65,"r2":95,"label":""},{"lo":126.221,"la":0.389,"de":31.8,"mw":5.8,"yr":1996,"ft":"T","s1":207,"d1":41,"r1":92,"s2":24,"d2":49,"r2":88,"label":""},{"lo":126.286,"la":3.065,"de":15.0,"mw":5.9,"yr":1996,"ft":"T","s1":351,"d1":20,"r1":56,"s2":206,"d2":74,"r2":101,"label":""},{"lo":126.463,"la":6.659,"de":53.0,"mw":5.9,"yr":1996,"ft":"T","s1":222,"d1":9,"r1":138,"s2":353,"d2":84,"r2":84,"label":""},{"lo":126.542,"la":2.905,"de":44.6,"mw":5.9,"yr":1996,"ft":"T","s1":191,"d1":21,"r1":84,"s2":17,"d2":69,"r2":92,"label":""},{"lo":127.254,"la":2.857,"de":33.0,"mw":5.6,"yr":1996,"ft":"T","s1":219,"d1":17,"r1":172,"s2":317,"d2":88,"r2":74,"label":""},{"lo":127.397,"la":4.97,"de":82.5,"mw":5.7,"yr":1996,"ft":"T","s1":7,"d1":26,"r1":138,"s2":135,"d2":73,"r2":70,"label":""},{"lo":128.354,"la":2.973,"de":40.0,"mw":5.6,"yr":1996,"ft":"T","s1":248,"d1":42,"r1":75,"s2":88,"d2":50,"r2":103,"label":""},{"lo":131.066,"la":-6.884,"de":66.2,"mw":5.8,"yr":1996,"ft":"S","s1":84,"d1":57,"r1":38,"s2":330,"d2":59,"r2":140,"label":""},{"lo":117.017,"la":-8.666,"de":154.3,"mw":5.7,"yr":1997,"ft":"N","s1":35,"d1":13,"r1":-147,"s2":273,"d2":83,"r2":-79,"label":""},{"lo":117.413,"la":-7.782,"de":282.9,"mw":5.6,"yr":1997,"ft":"T","s1":267,"d1":20,"r1":99,"s2":78,"d2":70,"r2":87,"label":""},{"lo":119.51,"la":-9.641,"de":44.6,"mw":5.9,"yr":1997,"ft":"T","s1":268,"d1":20,"r1":77,"s2":101,"d2":70,"r2":95,"label":""},{"lo":119.727,"la":-3.776,"de":34.5,"mw":5.9,"yr":1997,"ft":"T","s1":13,"d1":40,"r1":110,"s2":167,"d2":53,"r2":74,"label":""},{"lo":121.847,"la":-0.719,"de":27.5,"mw":5.5,"yr":1997,"ft":"S","s1":322,"d1":86,"r1":2,"s2":231,"d2":88,"r2":176,"label":""},{"lo":123.561,"la":6.756,"de":591.9,"mw":5.5,"yr":1997,"ft":"N","s1":248,"d1":21,"r1":-36,"s2":12,"d2":78,"r2":-107,"label":""},{"lo":123.823,"la":-0.127,"de":120.0,"mw":5.8,"yr":1997,"ft":"T","s1":143,"d1":40,"r1":51,"s2":9,"d2":60,"r2":118,"label":""},{"lo":124.066,"la":-0.895,"de":34.5,"mw":5.5,"yr":1997,"ft":"S","s1":206,"d1":81,"r1":175,"s2":297,"d2":85,"r2":9,"label":""},{"lo":124.073,"la":-0.149,"de":55.0,"mw":5.5,"yr":1997,"ft":"T","s1":229,"d1":35,"r1":120,"s2":14,"d2":61,"r2":71,"label":""},{"lo":125.299,"la":0.344,"de":48.2,"mw":5.8,"yr":1997,"ft":"T","s1":234,"d1":19,"r1":114,"s2":29,"d2":73,"r2":82,"label":""},{"lo":125.453,"la":5.679,"de":204.7,"mw":5.8,"yr":1997,"ft":"T","s1":148,"d1":24,"r1":91,"s2":327,"d2":66,"r2":90,"label":""},{"lo":125.884,"la":0.825,"de":43.0,"mw":5.7,"yr":1997,"ft":"T","s1":22,"d1":38,"r1":81,"s2":213,"d2":52,"r2":97,"label":""},{"lo":126.431,"la":5.436,"de":36.0,"mw":5.5,"yr":1997,"ft":"T","s1":197,"d1":32,"r1":93,"s2":14,"d2":58,"r2":88,"label":""},{"lo":126.646,"la":2.207,"de":34.0,"mw":5.8,"yr":1997,"ft":"T","s1":32,"d1":26,"r1":122,"s2":178,"d2":68,"r2":76,"label":""},{"lo":127.061,"la":2.294,"de":68.5,"mw":5.6,"yr":1997,"ft":"N","s1":174,"d1":40,"r1":-129,"s2":40,"d2":60,"r2":-62,"label":""},{"lo":128.237,"la":2.803,"de":131.4,"mw":5.8,"yr":1997,"ft":"S","s1":126,"d1":49,"r1":30,"s2":15,"d2":68,"r2":135,"label":""},{"lo":129.143,"la":-7.249,"de":128.5,"mw":5.6,"yr":1997,"ft":"S","s1":82,"d1":54,"r1":7,"s2":348,"d2":84,"r2":144,"label":""},{"lo":119.859,"la":-0.384,"de":36.1,"mw":5.9,"yr":1998,"ft":"T","s1":359,"d1":34,"r1":41,"s2":233,"d2":69,"r2":117,"label":""},{"lo":121.45,"la":-8.344,"de":22.0,"mw":5.8,"yr":1998,"ft":"T","s1":109,"d1":32,"r1":117,"s2":258,"d2":62,"r2":74,"label":""},{"lo":123.164,"la":-3.552,"de":54.0,"mw":5.7,"yr":1998,"ft":"N","s1":62,"d1":39,"r1":-74,"s2":222,"d2":53,"r2":-102,"label":""},{"lo":126.143,"la":5.167,"de":92.2,"mw":5.7,"yr":1998,"ft":"T","s1":325,"d1":20,"r1":60,"s2":177,"d2":73,"r2":101,"label":""},{"lo":126.263,"la":1.178,"de":30.7,"mw":5.6,"yr":1998,"ft":"T","s1":345,"d1":3,"r1":129,"s2":126,"d2":87,"r2":88,"label":""},{"lo":126.335,"la":6.293,"de":34.0,"mw":5.7,"yr":1998,"ft":"T","s1":238,"d1":36,"r1":152,"s2":351,"d2":74,"r2":57,"label":""},{"lo":126.543,"la":1.681,"de":33.6,"mw":5.5,"yr":1998,"ft":"T","s1":59,"d1":25,"r1":90,"s2":239,"d2":65,"r2":90,"label":""},{"lo":127.081,"la":-7.262,"de":281.9,"mw":5.7,"yr":1998,"ft":"T","s1":186,"d1":25,"r1":154,"s2":299,"d2":79,"r2":67,"label":""},{"lo":128.623,"la":2.921,"de":58.8,"mw":5.9,"yr":1998,"ft":"T","s1":26,"d1":27,"r1":86,"s2":211,"d2":63,"r2":92,"label":""},{"lo":128.659,"la":-7.018,"de":43.8,"mw":5.6,"yr":1998,"ft":"S","s1":135,"d1":74,"r1":-169,"s2":42,"d2":79,"r2":-16,"label":""},{"lo":129.115,"la":-4.099,"de":27.5,"mw":5.9,"yr":1998,"ft":"S","s1":94,"d1":55,"r1":34,"s2":343,"d2":63,"r2":140,"label":""},{"lo":129.248,"la":-4.514,"de":51.9,"mw":5.6,"yr":1998,"ft":"T","s1":105,"d1":44,"r1":83,"s2":295,"d2":47,"r2":97,"label":""},{"lo":130.163,"la":-6.031,"de":154.7,"mw":5.6,"yr":1998,"ft":"S","s1":135,"d1":47,"r1":-166,"s2":36,"d2":80,"r2":-44,"label":""},{"lo":117.089,"la":-7.028,"de":631.8,"mw":5.5,"yr":1999,"ft":"N","s1":55,"d1":43,"r1":-119,"s2":272,"d2":53,"r2":-66,"label":""},{"lo":119.484,"la":0.232,"de":64.4,"mw":5.5,"yr":1999,"ft":"S","s1":106,"d1":74,"r1":-177,"s2":15,"d2":87,"r2":-16,"label":""},{"lo":120.159,"la":-9.03,"de":64.0,"mw":5.5,"yr":1999,"ft":"S","s1":305,"d1":50,"r1":172,"s2":40,"d2":84,"r2":41,"label":""},{"lo":121.441,"la":-0.418,"de":51.3,"mw":5.5,"yr":1999,"ft":"S","s1":93,"d1":58,"r1":-31,"s2":201,"d2":64,"r2":-144,"label":""},{"lo":121.487,"la":-0.944,"de":15.0,"mw":5.7,"yr":1999,"ft":"N","s1":265,"d1":43,"r1":-93,"s2":89,"d2":47,"r2":-87,"label":""},{"lo":122.168,"la":5.255,"de":15.0,"mw":5.9,"yr":1999,"ft":"T","s1":336,"d1":32,"r1":80,"s2":168,"d2":59,"r2":96,"label":""},{"lo":122.492,"la":-1.776,"de":24.2,"mw":5.6,"yr":1999,"ft":"S","s1":49,"d1":70,"r1":163,"s2":145,"d2":74,"r2":21,"label":""},{"lo":122.702,"la":-0.279,"de":78.0,"mw":5.8,"yr":1999,"ft":"S","s1":58,"d1":49,"r1":126,"s2":191,"d2":52,"r2":56,"label":""},{"lo":122.909,"la":-0.155,"de":85.9,"mw":5.5,"yr":1999,"ft":"T","s1":226,"d1":29,"r1":67,"s2":72,"d2":63,"r2":102,"label":""},{"lo":123.484,"la":0.053,"de":135.3,"mw":5.7,"yr":1999,"ft":"T","s1":231,"d1":28,"r1":54,"s2":90,"d2":67,"r2":107,"label":""},{"lo":123.855,"la":5.625,"de":19.0,"mw":5.9,"yr":1999,"ft":"S","s1":157,"d1":45,"r1":99,"s2":325,"d2":46,"r2":81,"label":""},{"lo":124.313,"la":-0.034,"de":76.3,"mw":5.8,"yr":1999,"ft":"T","s1":243,"d1":40,"r1":118,"s2":29,"d2":55,"r2":69,"label":""},{"lo":125.119,"la":-0.138,"de":66.3,"mw":5.8,"yr":1999,"ft":"S","s1":263,"d1":46,"r1":171,"s2":359,"d2":83,"r2":44,"label":""},{"lo":125.674,"la":2.683,"de":76.4,"mw":5.5,"yr":1999,"ft":"T","s1":200,"d1":30,"r1":93,"s2":17,"d2":60,"r2":88,"label":""},{"lo":126.11,"la":0.565,"de":29.5,"mw":5.7,"yr":1999,"ft":"N","s1":211,"d1":13,"r1":-77,"s2":18,"d2":77,"r2":-93,"label":""},{"lo":126.205,"la":0.581,"de":15.0,"mw":5.6,"yr":1999,"ft":"N","s1":87,"d1":8,"r1":-169,"s2":346,"d2":89,"r2":-82,"label":""},{"lo":126.347,"la":3.802,"de":17.2,"mw":5.6,"yr":1999,"ft":"T","s1":298,"d1":23,"r1":45,"s2":165,"d2":74,"r2":106,"label":""},{"lo":126.528,"la":-2.975,"de":15.0,"mw":5.7,"yr":1999,"ft":"S","s1":149,"d1":41,"r1":142,"s2":270,"d2":66,"r2":56,"label":""},{"lo":126.641,"la":5.649,"de":21.1,"mw":5.5,"yr":1999,"ft":"S","s1":3,"d1":72,"r1":-4,"s2":95,"d2":87,"r2":-162,"label":""},{"lo":126.702,"la":2.355,"de":47.2,"mw":5.5,"yr":1999,"ft":"T","s1":31,"d1":27,"r1":89,"s2":212,"d2":63,"r2":90,"label":""},{"lo":126.709,"la":5.513,"de":51.3,"mw":5.7,"yr":1999,"ft":"S","s1":15,"d1":47,"r1":46,"s2":250,"d2":58,"r2":127,"label":""},{"lo":127.115,"la":2.077,"de":90.8,"mw":5.9,"yr":1999,"ft":"S","s1":301,"d1":48,"r1":4,"s2":208,"d2":87,"r2":138,"label":""},{"lo":127.273,"la":-0.688,"de":76.6,"mw":5.6,"yr":1999,"ft":"T","s1":351,"d1":37,"r1":157,"s2":100,"d2":76,"r2":55,"label":""},{"lo":127.914,"la":2.667,"de":37.0,"mw":5.7,"yr":1999,"ft":"S","s1":4,"d1":65,"r1":5,"s2":273,"d2":86,"r2":155,"label":""},{"lo":128.088,"la":3.282,"de":60.0,"mw":5.7,"yr":1999,"ft":"S","s1":28,"d1":47,"r1":111,"s2":179,"d2":47,"r2":70,"label":""},{"lo":128.155,"la":-2.889,"de":26.1,"mw":5.7,"yr":1999,"ft":"T","s1":76,"d1":17,"r1":35,"s2":312,"d2":80,"r2":104,"label":""},{"lo":128.288,"la":1.674,"de":54.6,"mw":5.7,"yr":1999,"ft":"T","s1":101,"d1":22,"r1":6,"s2":5,"d2":88,"r2":112,"label":""},{"lo":128.658,"la":-7.122,"de":43.3,"mw":5.8,"yr":1999,"ft":"S","s1":134,"d1":79,"r1":171,"s2":225,"d2":82,"r2":11,"label":""},{"lo":129.336,"la":-6.94,"de":196.6,"mw":5.8,"yr":1999,"ft":"T","s1":287,"d1":36,"r1":135,"s2":56,"d2":65,"r2":63,"label":""},{"lo":129.686,"la":-3.068,"de":24.6,"mw":5.5,"yr":1999,"ft":"T","s1":146,"d1":15,"r1":97,"s2":319,"d2":75,"r2":88,"label":""},{"lo":131.331,"la":-3.986,"de":19.0,"mw":5.9,"yr":1999,"ft":"T","s1":168,"d1":18,"r1":102,"s2":336,"d2":73,"r2":86,"label":""},{"lo":131.43,"la":-3.857,"de":17.2,"mw":5.6,"yr":1999,"ft":"T","s1":183,"d1":20,"r1":111,"s2":340,"d2":72,"r2":83,"label":""},{"lo":118.764,"la":-9.691,"de":88.5,"mw":5.6,"yr":2000,"ft":"S","s1":19,"d1":62,"r1":-164,"s2":282,"d2":76,"r2":-29,"label":""},{"lo":119.378,"la":-9.974,"de":27.0,"mw":5.9,"yr":2000,"ft":"T","s1":277,"d1":30,"r1":97,"s2":89,"d2":60,"r2":86,"label":""},{"lo":120.151,"la":1.091,"de":43.4,"mw":5.6,"yr":2000,"ft":"T","s1":55,"d1":15,"r1":64,"s2":262,"d2":76,"r2":97,"label":""},{"lo":120.613,"la":-7.967,"de":15.0,"mw":5.8,"yr":2000,"ft":"S","s1":228,"d1":48,"r1":61,"s2":88,"d2":50,"r2":118,"label":""},{"lo":120.646,"la":-7.973,"de":41.1,"mw":5.6,"yr":2000,"ft":"T","s1":234,"d1":40,"r1":70,"s2":80,"d2":53,"r2":106,"label":""},{"lo":121.286,"la":0.482,"de":104.2,"mw":5.6,"yr":2000,"ft":"S","s1":5,"d1":63,"r1":-19,"s2":104,"d2":73,"r2":-152,"label":""},{"lo":121.554,"la":-0.847,"de":33.0,"mw":5.5,"yr":2000,"ft":"N","s1":124,"d1":8,"r1":-49,"s2":262,"d2":84,"r2":-95,"label":""},{"lo":122.051,"la":0.267,"de":179.0,"mw":5.5,"yr":2000,"ft":"S","s1":316,"d1":45,"r1":108,"s2":112,"d2":47,"r2":73,"label":""},{"lo":122.073,"la":0.253,"de":184.2,"mw":5.5,"yr":2000,"ft":"S","s1":79,"d1":46,"r1":71,"s2":285,"d2":47,"r2":109,"label":""},{"lo":122.551,"la":-2.54,"de":55.5,"mw":5.6,"yr":2000,"ft":"S","s1":106,"d1":76,"r1":5,"s2":15,"d2":85,"r2":166,"label":""},{"lo":122.678,"la":-7.485,"de":596.4,"mw":5.5,"yr":2000,"ft":"S","s1":121,"d1":54,"r1":153,"s2":227,"d2":69,"r2":39,"label":""},{"lo":123.134,"la":-1.397,"de":29.9,"mw":5.5,"yr":2000,"ft":"S","s1":313,"d1":64,"r1":12,"s2":218,"d2":80,"r2":153,"label":""},{"lo":123.212,"la":5.069,"de":578.7,"mw":5.7,"yr":2000,"ft":"N","s1":252,"d1":17,"r1":-63,"s2":43,"d2":75,"r2":-98,"label":""},{"lo":123.247,"la":-4.196,"de":15.0,"mw":5.6,"yr":2000,"ft":"T","s1":218,"d1":16,"r1":123,"s2":3,"d2":77,"r2":81,"label":""},{"lo":123.305,"la":-1.577,"de":33.0,"mw":5.6,"yr":2000,"ft":"S","s1":42,"d1":77,"r1":178,"s2":132,"d2":88,"r2":13,"label":""},{"lo":123.354,"la":-1.42,"de":41.7,"mw":5.6,"yr":2000,"ft":"S","s1":215,"d1":51,"r1":137,"s2":336,"d2":58,"r2":48,"label":""},{"lo":123.359,"la":-1.215,"de":40.3,"mw":5.7,"yr":2000,"ft":"S","s1":219,"d1":77,"r1":175,"s2":310,"d2":85,"r2":13,"label":""},{"lo":125.773,"la":5.762,"de":116.4,"mw":5.8,"yr":2000,"ft":"T","s1":197,"d1":14,"r1":118,"s2":348,"d2":78,"r2":83,"label":""},{"lo":125.906,"la":-7.096,"de":517.5,"mw":5.8,"yr":2000,"ft":"N","s1":358,"d1":43,"r1":-117,"s2":213,"d2":53,"r2":-67,"label":""},{"lo":126.242,"la":0.931,"de":23.4,"mw":5.5,"yr":2000,"ft":"T","s1":21,"d1":42,"r1":90,"s2":201,"d2":48,"r2":90,"label":""},{"lo":126.266,"la":1.279,"de":42.7,"mw":5.8,"yr":2000,"ft":"T","s1":205,"d1":41,"r1":75,"s2":45,"d2":51,"r2":103,"label":""},{"lo":126.272,"la":1.295,"de":37.2,"mw":5.5,"yr":2000,"ft":"T","s1":23,"d1":30,"r1":104,"s2":187,"d2":61,"r2":82,"label":""},{"lo":126.438,"la":0.152,"de":114.8,"mw":5.6,"yr":2000,"ft":"T","s1":295,"d1":22,"r1":3,"s2":202,"d2":89,"r2":112,"label":""},{"lo":126.439,"la":4.222,"de":80.0,"mw":5.7,"yr":2000,"ft":"N","s1":150,"d1":35,"r1":-48,"s2":283,"d2":64,"r2":-115,"label":""},{"lo":126.579,"la":4.352,"de":58.9,"mw":5.6,"yr":2000,"ft":"T","s1":223,"d1":43,"r1":104,"s2":25,"d2":49,"r2":78,"label":""},{"lo":126.82,"la":4.943,"de":55.5,"mw":5.5,"yr":2000,"ft":"S","s1":170,"d1":79,"r1":3,"s2":80,"d2":87,"r2":169,"label":""},{"lo":127.068,"la":5.694,"de":133.3,"mw":5.7,"yr":2000,"ft":"S","s1":104,"d1":45,"r1":81,"s2":297,"d2":46,"r2":99,"label":""},{"lo":127.174,"la":5.737,"de":83.6,"mw":5.7,"yr":2000,"ft":"S","s1":192,"d1":74,"r1":165,"s2":287,"d2":76,"r2":17,"label":""},{"lo":127.334,"la":-4.046,"de":15.0,"mw":5.8,"yr":2000,"ft":"S","s1":241,"d1":76,"r1":5,"s2":150,"d2":85,"r2":166,"label":""},{"lo":127.38,"la":0.05,"de":120.9,"mw":5.7,"yr":2000,"ft":"N","s1":116,"d1":36,"r1":-23,"s2":225,"d2":77,"r2":-124,"label":""},{"lo":127.388,"la":-4.054,"de":29.1,"mw":5.7,"yr":2000,"ft":"S","s1":349,"d1":70,"r1":177,"s2":81,"d2":87,"r2":20,"label":""},{"lo":127.442,"la":1.123,"de":147.9,"mw":5.9,"yr":2000,"ft":"S","s1":184,"d1":44,"r1":146,"s2":300,"d2":67,"r2":51,"label":""},{"lo":128.034,"la":3.155,"de":91.8,"mw":5.9,"yr":2000,"ft":"S","s1":16,"d1":40,"r1":148,"s2":131,"d2":70,"r2":55,"label":""},{"lo":128.215,"la":3.913,"de":25.0,"mw":5.5,"yr":2000,"ft":"T","s1":158,"d1":24,"r1":61,"s2":9,"d2":69,"r2":102,"label":""},{"lo":128.269,"la":3.959,"de":15.0,"mw":5.5,"yr":2000,"ft":"T","s1":160,"d1":23,"r1":50,"s2":23,"d2":73,"r2":105,"label":""},{"lo":128.455,"la":4.022,"de":15.0,"mw":5.7,"yr":2000,"ft":"T","s1":166,"d1":24,"r1":73,"s2":4,"d2":67,"r2":97,"label":""},{"lo":128.931,"la":-7.027,"de":226.1,"mw":5.9,"yr":2000,"ft":"T","s1":184,"d1":23,"r1":0,"s2":94,"d2":90,"r2":113,"label":""},{"lo":129.004,"la":-6.943,"de":170.0,"mw":5.5,"yr":2000,"ft":"T","s1":293,"d1":32,"r1":103,"s2":98,"d2":59,"r2":82,"label":""},{"lo":129.193,"la":-7.206,"de":169.2,"mw":5.5,"yr":2000,"ft":"N","s1":13,"d1":28,"r1":-115,"s2":221,"d2":65,"r2":-78,"label":""},{"lo":129.3,"la":-6.859,"de":175.4,"mw":5.6,"yr":2000,"ft":"S","s1":63,"d1":57,"r1":8,"s2":329,"d2":83,"r2":146,"label":""},{"lo":129.348,"la":-1.179,"de":15.0,"mw":5.5,"yr":2000,"ft":"N","s1":138,"d1":15,"r1":-107,"s2":335,"d2":76,"r2":-86,"label":""},{"lo":130.209,"la":-6.377,"de":146.1,"mw":5.5,"yr":2000,"ft":"S","s1":308,"d1":53,"r1":138,"s2":66,"d2":57,"r2":45,"label":""},{"lo":130.309,"la":-5.845,"de":177.2,"mw":5.5,"yr":2000,"ft":"N","s1":344,"d1":16,"r1":-125,"s2":200,"d2":77,"r2":-81,"label":""},{"lo":115.042,"la":-11.375,"de":15.0,"mw":5.6,"yr":2001,"ft":"N","s1":82,"d1":32,"r1":-113,"s2":288,"d2":61,"r2":-77,"label":""},{"lo":122.97,"la":0.043,"de":165.5,"mw":5.6,"yr":2001,"ft":"S","s1":312,"d1":45,"r1":121,"s2":93,"d2":52,"r2":63,"label":""},{"lo":123.247,"la":-4.236,"de":16.0,"mw":5.6,"yr":2001,"ft":"T","s1":228,"d1":11,"r1":142,"s2":355,"d2":83,"r2":82,"label":""},{"lo":123.885,"la":-4.561,"de":15.0,"mw":5.5,"yr":2001,"ft":"S","s1":97,"d1":44,"r1":9,"s2":1,"d2":84,"r2":133,"label":""},{"lo":123.917,"la":-4.855,"de":28.0,"mw":5.7,"yr":2001,"ft":"S","s1":6,"d1":74,"r1":165,"s2":101,"d2":76,"r2":17,"label":""},{"lo":125.691,"la":1.443,"de":74.1,"mw":5.7,"yr":2001,"ft":"T","s1":223,"d1":26,"r1":92,"s2":41,"d2":64,"r2":89,"label":""},{"lo":126.299,"la":0.462,"de":26.7,"mw":5.8,"yr":2001,"ft":"S","s1":183,"d1":53,"r1":43,"s2":64,"d2":58,"r2":134,"label":""},{"lo":126.344,"la":2.49,"de":33.3,"mw":5.6,"yr":2001,"ft":"T","s1":4,"d1":28,"r1":31,"s2":246,"d2":76,"r2":115,"label":""},{"lo":126.354,"la":1.559,"de":34.0,"mw":5.8,"yr":2001,"ft":"S","s1":190,"d1":47,"r1":45,"s2":65,"d2":59,"r2":127,"label":""},{"lo":126.399,"la":1.557,"de":38.8,"mw":5.7,"yr":2001,"ft":"T","s1":197,"d1":34,"r1":67,"s2":44,"d2":60,"r2":105,"label":""},{"lo":126.506,"la":1.83,"de":44.0,"mw":5.7,"yr":2001,"ft":"T","s1":50,"d1":34,"r1":114,"s2":202,"d2":59,"r2":75,"label":""},{"lo":126.529,"la":2.874,"de":38.1,"mw":5.5,"yr":2001,"ft":"T","s1":165,"d1":20,"r1":66,"s2":10,"d2":71,"r2":98,"label":""},{"lo":126.842,"la":6.917,"de":15.0,"mw":5.5,"yr":2001,"ft":"T","s1":225,"d1":33,"r1":135,"s2":355,"d2":67,"r2":65,"label":""},{"lo":126.852,"la":6.582,"de":21.4,"mw":5.8,"yr":2001,"ft":"S","s1":248,"d1":59,"r1":143,"s2":359,"d2":59,"r2":37,"label":""},{"lo":126.867,"la":6.772,"de":24.0,"mw":5.6,"yr":2001,"ft":"T","s1":189,"d1":34,"r1":70,"s2":32,"d2":58,"r2":103,"label":""},{"lo":126.923,"la":6.622,"de":54.3,"mw":5.5,"yr":2001,"ft":"S","s1":97,"d1":56,"r1":-5,"s2":190,"d2":86,"r2":-146,"label":""},{"lo":126.995,"la":2.809,"de":33.0,"mw":5.9,"yr":2001,"ft":"T","s1":206,"d1":27,"r1":89,"s2":28,"d2":63,"r2":91,"label":""},{"lo":127.349,"la":5.846,"de":25.0,"mw":5.7,"yr":2001,"ft":"T","s1":142,"d1":20,"r1":42,"s2":12,"d2":77,"r2":105,"label":""},{"lo":130.074,"la":-5.969,"de":24.2,"mw":5.5,"yr":2001,"ft":"S","s1":60,"d1":60,"r1":3,"s2":328,"d2":88,"r2":150,"label":""},{"lo":130.742,"la":-5.645,"de":75.4,"mw":5.6,"yr":2001,"ft":"S","s1":302,"d1":51,"r1":137,"s2":63,"d2":58,"r2":48,"label":""},{"lo":117.26,"la":-11.238,"de":24.0,"mw":5.5,"yr":2002,"ft":"N","s1":250,"d1":41,"r1":-107,"s2":92,"d2":51,"r2":-76,"label":""},{"lo":118.616,"la":-9.285,"de":63.7,"mw":5.9,"yr":2002,"ft":"S","s1":116,"d1":79,"r1":173,"s2":207,"d2":83,"r2":12,"label":""},{"lo":119.901,"la":0.495,"de":20.0,"mw":5.9,"yr":2002,"ft":"S","s1":339,"d1":53,"r1":-24,"s2":84,"d2":71,"r2":-141,"label":""},{"lo":122.32,"la":0.68,"de":85.5,"mw":5.7,"yr":2002,"ft":"S","s1":18,"d1":53,"r1":20,"s2":275,"d2":74,"r2":141,"label":""},{"lo":122.752,"la":1.295,"de":28.0,"mw":5.6,"yr":2002,"ft":"T","s1":83,"d1":19,"r1":73,"s2":281,"d2":72,"r2":96,"label":""},{"lo":123.158,"la":4.983,"de":574.3,"mw":5.7,"yr":2002,"ft":"N","s1":179,"d1":17,"r1":-111,"s2":21,"d2":74,"r2":-84,"label":""},{"lo":123.28,"la":-4.191,"de":15.0,"mw":5.5,"yr":2002,"ft":"T","s1":225,"d1":27,"r1":143,"s2":349,"d2":74,"r2":68,"label":""},{"lo":124.382,"la":5.304,"de":27.9,"mw":5.7,"yr":2002,"ft":"S","s1":239,"d1":87,"r1":-178,"s2":149,"d2":88,"r2":-3,"label":""},{"lo":124.406,"la":5.283,"de":40.0,"mw":5.7,"yr":2002,"ft":"S","s1":232,"d1":75,"r1":-174,"s2":140,"d2":84,"r2":-15,"label":""},{"lo":125.377,"la":3.507,"de":48.0,"mw":5.5,"yr":2002,"ft":"S","s1":46,"d1":44,"r1":126,"s2":180,"d2":56,"r2":60,"label":""},{"lo":125.379,"la":1.096,"de":79.8,"mw":5.5,"yr":2002,"ft":"T","s1":228,"d1":23,"r1":108,"s2":28,"d2":68,"r2":82,"label":""},{"lo":125.411,"la":-7.003,"de":512.3,"mw":5.7,"yr":2002,"ft":"S","s1":200,"d1":55,"r1":-149,"s2":91,"d2":65,"r2":-39,"label":""},{"lo":126.273,"la":0.911,"de":34.4,"mw":5.6,"yr":2002,"ft":"T","s1":51,"d1":39,"r1":123,"s2":191,"d2":58,"r2":66,"label":""},{"lo":126.288,"la":3.026,"de":40.1,"mw":5.7,"yr":2002,"ft":"N","s1":277,"d1":19,"r1":-160,"s2":168,"d2":84,"r2":-72,"label":""},{"lo":126.319,"la":4.585,"de":54.0,"mw":5.5,"yr":2002,"ft":"T","s1":217,"d1":16,"r1":119,"s2":7,"d2":76,"r2":82,"label":""},{"lo":126.32,"la":6.437,"de":39.6,"mw":5.6,"yr":2002,"ft":"T","s1":217,"d1":34,"r1":145,"s2":338,"d2":71,"r2":61,"label":""},{"lo":126.392,"la":1.511,"de":21.0,"mw":5.9,"yr":2002,"ft":"N","s1":55,"d1":16,"r1":-71,"s2":215,"d2":75,"r2":-95,"label":""},{"lo":127.087,"la":-1.143,"de":20.0,"mw":5.9,"yr":2002,"ft":"T","s1":330,"d1":13,"r1":78,"s2":163,"d2":77,"r2":93,"label":""},{"lo":127.238,"la":1.832,"de":114.1,"mw":5.9,"yr":2002,"ft":"T","s1":346,"d1":24,"r1":16,"s2":242,"d2":84,"r2":114,"label":""},{"lo":128.109,"la":1.395,"de":124.5,"mw":5.7,"yr":2002,"ft":"S","s1":290,"d1":44,"r1":131,"s2":60,"d2":59,"r2":58,"label":""},{"lo":128.303,"la":2.646,"de":200.7,"mw":5.6,"yr":2002,"ft":"T","s1":101,"d1":29,"r1":153,"s2":215,"d2":77,"r2":64,"label":""},{"lo":128.995,"la":-6.888,"de":46.4,"mw":5.5,"yr":2002,"ft":"S","s1":46,"d1":83,"r1":-2,"s2":136,"d2":88,"r2":-173,"label":""},{"lo":130.311,"la":-6.504,"de":101.5,"mw":5.5,"yr":2002,"ft":"T","s1":273,"d1":38,"r1":89,"s2":95,"d2":52,"r2":91,"label":""},{"lo":130.61,"la":-6.067,"de":143.0,"mw":5.5,"yr":2002,"ft":"N","s1":11,"d1":8,"r1":-99,"s2":199,"d2":82,"r2":-89,"label":""},{"lo":130.755,"la":-5.654,"de":88.4,"mw":5.6,"yr":2002,"ft":"S","s1":307,"d1":52,"r1":138,"s2":66,"d2":58,"r2":46,"label":""},{"lo":117.185,"la":-10.211,"de":43.0,"mw":5.6,"yr":2003,"ft":"T","s1":306,"d1":29,"r1":112,"s2":101,"d2":64,"r2":78,"label":""},{"lo":117.788,"la":-8.747,"de":27.2,"mw":5.5,"yr":2003,"ft":"S","s1":89,"d1":45,"r1":176,"s2":183,"d2":87,"r2":45,"label":""},{"lo":118.524,"la":-8.807,"de":19.8,"mw":5.5,"yr":2003,"ft":"S","s1":83,"d1":74,"r1":165,"s2":177,"d2":76,"r2":16,"label":""},{"lo":120.495,"la":1.158,"de":41.8,"mw":5.5,"yr":2003,"ft":"T","s1":125,"d1":17,"r1":113,"s2":281,"d2":75,"r2":83,"label":""},{"lo":121.374,"la":-8.316,"de":39.5,"mw":5.5,"yr":2003,"ft":"T","s1":79,"d1":26,"r1":81,"s2":269,"d2":64,"r2":94,"label":""},{"lo":122.35,"la":0.599,"de":82.1,"mw":5.9,"yr":2003,"ft":"S","s1":266,"d1":60,"r1":169,"s2":1,"d2":81,"r2":30,"label":""},{"lo":122.682,"la":1.947,"de":459.9,"mw":5.8,"yr":2003,"ft":"S","s1":264,"d1":83,"r1":-2,"s2":354,"d2":88,"r2":-173,"label":""},{"lo":122.697,"la":-7.207,"de":584.6,"mw":5.6,"yr":2003,"ft":"S","s1":224,"d1":60,"r1":-154,"s2":121,"d2":67,"r2":-32,"label":""},{"lo":122.945,"la":-0.163,"de":96.3,"mw":5.5,"yr":2003,"ft":"T","s1":68,"d1":43,"r1":113,"s2":218,"d2":51,"r2":70,"label":""},{"lo":123.521,"la":0.153,"de":120.6,"mw":5.5,"yr":2003,"ft":"T","s1":248,"d1":35,"r1":103,"s2":52,"d2":56,"r2":81,"label":""},{"lo":123.625,"la":-9.014,"de":111.7,"mw":5.5,"yr":2003,"ft":"T","s1":335,"d1":23,"r1":176,"s2":69,"d2":88,"r2":67,"label":""},{"lo":123.646,"la":-0.45,"de":48.7,"mw":5.5,"yr":2003,"ft":"S","s1":171,"d1":51,"r1":52,"s2":42,"d2":52,"r2":127,"label":""},{"lo":123.94,"la":0.151,"de":119.9,"mw":5.5,"yr":2003,"ft":"T","s1":176,"d1":36,"r1":89,"s2":358,"d2":54,"r2":91,"label":""},{"lo":124.58,"la":0.136,"de":77.2,"mw":5.8,"yr":2003,"ft":"S","s1":96,"d1":54,"r1":20,"s2":354,"d2":74,"r2":142,"label":""},{"lo":125.166,"la":-0.212,"de":45.0,"mw":5.5,"yr":2003,"ft":"T","s1":246,"d1":27,"r1":117,"s2":36,"d2":67,"r2":77,"label":""},{"lo":125.407,"la":-7.05,"de":533.1,"mw":5.9,"yr":2003,"ft":"N","s1":191,"d1":33,"r1":-148,"s2":73,"d2":73,"r2":-61,"label":""},{"lo":126.177,"la":0.207,"de":27.5,"mw":5.5,"yr":2003,"ft":"S","s1":63,"d1":39,"r1":165,"s2":165,"d2":81,"r2":52,"label":""},{"lo":126.411,"la":1.236,"de":45.8,"mw":5.5,"yr":2003,"ft":"T","s1":28,"d1":36,"r1":107,"s2":188,"d2":56,"r2":78,"label":""},{"lo":126.682,"la":2.078,"de":67.2,"mw":5.6,"yr":2003,"ft":"S","s1":78,"d1":52,"r1":152,"s2":187,"d2":68,"r2":41,"label":""},{"lo":126.791,"la":-0.944,"de":26.1,"mw":5.6,"yr":2003,"ft":"N","s1":276,"d1":29,"r1":-7,"s2":12,"d2":87,"r2":-119,"label":""},{"lo":126.88,"la":2.041,"de":15.0,"mw":5.6,"yr":2003,"ft":"N","s1":229,"d1":6,"r1":-152,"s2":111,"d2":87,"r2":-85,"label":""},{"lo":126.991,"la":-1.062,"de":36.8,"mw":5.7,"yr":2003,"ft":"T","s1":322,"d1":20,"r1":66,"s2":168,"d2":72,"r2":99,"label":""},{"lo":127.013,"la":5.183,"de":15.0,"mw":5.5,"yr":2003,"ft":"T","s1":151,"d1":10,"r1":83,"s2":338,"d2":80,"r2":91,"label":""},{"lo":127.033,"la":2.001,"de":15.0,"mw":5.8,"yr":2003,"ft":"T","s1":158,"d1":8,"r1":130,"s2":298,"d2":84,"r2":85,"label":""},{"lo":127.358,"la":1.562,"de":137.8,"mw":5.8,"yr":2003,"ft":"S","s1":283,"d1":44,"r1":-12,"s2":22,"d2":82,"r2":-133,"label":""},{"lo":127.39,"la":-3.119,"de":24.0,"mw":5.6,"yr":2003,"ft":"T","s1":105,"d1":29,"r1":72,"s2":305,"d2":62,"r2":100,"label":""},{"lo":127.856,"la":-7.56,"de":172.5,"mw":5.9,"yr":2003,"ft":"S","s1":317,"d1":51,"r1":137,"s2":77,"d2":58,"r2":48,"label":""},{"lo":129.023,"la":-7.796,"de":50.4,"mw":5.6,"yr":2003,"ft":"T","s1":232,"d1":44,"r1":93,"s2":48,"d2":46,"r2":87,"label":""},{"lo":129.836,"la":-5.361,"de":41.7,"mw":5.8,"yr":2003,"ft":"S","s1":65,"d1":76,"r1":-2,"s2":155,"d2":88,"r2":-166,"label":""},{"lo":130.146,"la":-2.964,"de":15.0,"mw":5.5,"yr":2003,"ft":"T","s1":110,"d1":15,"r1":75,"s2":305,"d2":75,"r2":94,"label":""},{"lo":130.193,"la":-2.937,"de":15.0,"mw":5.6,"yr":2003,"ft":"T","s1":90,"d1":18,"r1":57,"s2":305,"d2":75,"r2":100,"label":""},{"lo":130.894,"la":-3.232,"de":16.3,"mw":5.6,"yr":2003,"ft":"T","s1":133,"d1":20,"r1":93,"s2":310,"d2":70,"r2":89,"label":""},{"lo":114.65,"la":-8.669,"de":105.2,"mw":5.5,"yr":2004,"ft":"S","s1":213,"d1":51,"r1":151,"s2":322,"d2":68,"r2":43,"label":""},{"lo":115.788,"la":-8.31,"de":35.6,"mw":5.8,"yr":2004,"ft":"S","s1":349,"d1":63,"r1":162,"s2":87,"d2":74,"r2":28,"label":""},{"lo":123.36,"la":-0.665,"de":12.0,"mw":5.5,"yr":2004,"ft":"S","s1":281,"d1":47,"r1":121,"s2":59,"d2":51,"r2":61,"label":""},{"lo":124.343,"la":-8.861,"de":95.4,"mw":5.5,"yr":2004,"ft":"N","s1":49,"d1":13,"r1":-20,"s2":158,"d2":85,"r2":-103,"label":""},{"lo":124.812,"la":-8.174,"de":17.0,"mw":5.6,"yr":2004,"ft":"T","s1":91,"d1":24,"r1":118,"s2":241,"d2":69,"r2":78,"label":""},{"lo":124.932,"la":-0.01,"de":30.0,"mw":5.6,"yr":2004,"ft":"T","s1":254,"d1":27,"r1":142,"s2":19,"d2":73,"r2":68,"label":""},{"lo":125.068,"la":-8.059,"de":13.4,"mw":5.5,"yr":2004,"ft":"T","s1":67,"d1":24,"r1":115,"s2":220,"d2":68,"r2":79,"label":""},{"lo":125.106,"la":-2.131,"de":12.0,"mw":5.6,"yr":2004,"ft":"T","s1":345,"d1":41,"r1":121,"s2":126,"d2":56,"r2":66,"label":""},{"lo":125.277,"la":5.885,"de":101.3,"mw":5.5,"yr":2004,"ft":"S","s1":292,"d1":68,"r1":168,"s2":26,"d2":79,"r2":22,"label":""},{"lo":126.186,"la":-3.405,"de":12.0,"mw":5.5,"yr":2004,"ft":"S","s1":92,"d1":45,"r1":-103,"s2":290,"d2":46,"r2":-78,"label":""},{"lo":126.411,"la":6.591,"de":60.0,"mw":5.7,"yr":2004,"ft":"T","s1":227,"d1":34,"r1":153,"s2":340,"d2":75,"r2":59,"label":""},{"lo":126.437,"la":5.389,"de":27.0,"mw":5.8,"yr":2004,"ft":"T","s1":153,"d1":30,"r1":26,"s2":40,"d2":77,"r2":118,"label":""},{"lo":126.695,"la":2.07,"de":35.3,"mw":5.5,"yr":2004,"ft":"T","s1":33,"d1":36,"r1":92,"s2":211,"d2":54,"r2":88,"label":""},{"lo":126.92,"la":6.318,"de":124.0,"mw":5.5,"yr":2004,"ft":"T","s1":157,"d1":30,"r1":76,"s2":353,"d2":61,"r2":98,"label":""},{"lo":126.943,"la":6.292,"de":209.6,"mw":5.5,"yr":2004,"ft":"S","s1":1,"d1":49,"r1":140,"s2":119,"d2":61,"r2":48,"label":""},{"lo":128.041,"la":-6.314,"de":384.8,"mw":5.5,"yr":2004,"ft":"N","s1":96,"d1":21,"r1":-28,"s2":213,"d2":80,"r2":-109,"label":""},{"lo":128.373,"la":-7.352,"de":143.3,"mw":5.8,"yr":2004,"ft":"T","s1":66,"d1":37,"r1":94,"s2":241,"d2":53,"r2":87,"label":""},{"lo":128.386,"la":3.615,"de":20.0,"mw":5.6,"yr":2004,"ft":"T","s1":163,"d1":36,"r1":68,"s2":9,"d2":57,"r2":105,"label":""},{"lo":129.121,"la":-6.184,"de":246.5,"mw":5.6,"yr":2004,"ft":"T","s1":83,"d1":31,"r1":79,"s2":276,"d2":60,"r2":97,"label":""},{"lo":129.977,"la":-6.39,"de":165.1,"mw":5.7,"yr":2004,"ft":"N","s1":83,"d1":5,"r1":-22,"s2":195,"d2":88,"r2":-94,"label":""},{"lo":130.218,"la":-6.567,"de":109.6,"mw":5.5,"yr":2004,"ft":"S","s1":54,"d1":59,"r1":31,"s2":306,"d2":63,"r2":145,"label":""},{"lo":130.435,"la":-6.689,"de":94.0,"mw":5.5,"yr":2004,"ft":"S","s1":325,"d1":47,"r1":138,"s2":87,"d2":61,"r2":52,"label":""},{"lo":130.528,"la":-6.066,"de":90.7,"mw":5.8,"yr":2004,"ft":"S","s1":297,"d1":52,"r1":136,"s2":58,"d2":57,"r2":47,"label":""},{"lo":119.963,"la":-1.174,"de":12.0,"mw":5.9,"yr":2005,"ft":"S","s1":80,"d1":44,"r1":-141,"s2":320,"d2":64,"r2":-53,"label":""},{"lo":124.238,"la":-9.911,"de":12.0,"mw":5.5,"yr":2005,"ft":"T","s1":205,"d1":30,"r1":27,"s2":91,"d2":77,"r2":118,"label":""},{"lo":124.825,"la":-7.945,"de":12.0,"mw":5.8,"yr":2005,"ft":"S","s1":51,"d1":78,"r1":171,"s2":143,"d2":81,"r2":12,"label":""},{"lo":125.148,"la":-0.157,"de":17.0,"mw":5.8,"yr":2005,"ft":"T","s1":265,"d1":24,"r1":157,"s2":16,"d2":81,"r2":68,"label":""},{"lo":125.245,"la":5.186,"de":178.7,"mw":5.9,"yr":2005,"ft":"N","s1":209,"d1":21,"r1":-41,"s2":337,"d2":76,"r2":-107,"label":""},{"lo":125.768,"la":1.414,"de":27.0,"mw":5.5,"yr":2005,"ft":"T","s1":285,"d1":4,"r1":55,"s2":141,"d2":86,"r2":93,"label":""},{"lo":125.825,"la":1.769,"de":88.0,"mw":5.7,"yr":2005,"ft":"S","s1":309,"d1":55,"r1":151,"s2":57,"d2":67,"r2":39,"label":""},{"lo":126.283,"la":0.77,"de":38.0,"mw":5.7,"yr":2005,"ft":"T","s1":16,"d1":36,"r1":89,"s2":197,"d2":54,"r2":91,"label":""},{"lo":126.297,"la":6.041,"de":24.0,"mw":5.5,"yr":2005,"ft":"T","s1":151,"d1":35,"r1":43,"s2":24,"d2":67,"r2":117,"label":""},{"lo":126.386,"la":5.905,"de":45.9,"mw":5.8,"yr":2005,"ft":"T","s1":342,"d1":40,"r1":87,"s2":166,"d2":50,"r2":92,"label":""},{"lo":126.407,"la":2.67,"de":26.5,"mw":5.9,"yr":2005,"ft":"S","s1":131,"d1":45,"r1":57,"s2":354,"d2":54,"r2":119,"label":""},{"lo":126.48,"la":2.966,"de":51.0,"mw":5.9,"yr":2005,"ft":"T","s1":200,"d1":29,"r1":103,"s2":4,"d2":62,"r2":83,"label":""},{"lo":126.529,"la":2.75,"de":25.5,"mw":5.9,"yr":2005,"ft":"T","s1":53,"d1":35,"r1":152,"s2":167,"d2":74,"r2":58,"label":""},{"lo":126.572,"la":2.087,"de":41.0,"mw":5.9,"yr":2005,"ft":"T","s1":27,"d1":38,"r1":93,"s2":204,"d2":52,"r2":88,"label":""},{"lo":127.325,"la":-3.592,"de":15.0,"mw":5.7,"yr":2005,"ft":"S","s1":184,"d1":64,"r1":154,"s2":286,"d2":67,"r2":28,"label":""},{"lo":128.15,"la":3.008,"de":81.4,"mw":5.9,"yr":2005,"ft":"T","s1":343,"d1":36,"r1":84,"s2":170,"d2":54,"r2":94,"label":""},{"lo":128.713,"la":-5.902,"de":317.8,"mw":5.5,"yr":2005,"ft":"S","s1":79,"d1":50,"r1":0,"s2":348,"d2":90,"r2":140,"label":""},{"lo":128.819,"la":-4.003,"de":12.0,"mw":5.6,"yr":2005,"ft":"T","s1":290,"d1":44,"r1":111,"s2":82,"d2":49,"r2":70,"label":""},{"lo":128.944,"la":-3.1,"de":23.0,"mw":5.9,"yr":2005,"ft":"S","s1":63,"d1":52,"r1":30,"s2":314,"d2":67,"r2":138,"label":""},{"lo":129.022,"la":-7.872,"de":33.7,"mw":5.5,"yr":2005,"ft":"T","s1":55,"d1":39,"r1":86,"s2":239,"d2":51,"r2":93,"label":""},{"lo":129.221,"la":-6.958,"de":160.2,"mw":5.5,"yr":2005,"ft":"S","s1":314,"d1":66,"r1":178,"s2":45,"d2":88,"r2":24,"label":""},{"lo":129.568,"la":-6.764,"de":28.0,"mw":5.6,"yr":2005,"ft":"T","s1":109,"d1":3,"r1":21,"s2":358,"d2":89,"r2":93,"label":""},{"lo":129.996,"la":-5.824,"de":22.1,"mw":5.7,"yr":2005,"ft":"S","s1":62,"d1":81,"r1":4,"s2":331,"d2":86,"r2":171,"label":""},{"lo":131.405,"la":-6.829,"de":60.5,"mw":5.7,"yr":2005,"ft":"S","s1":339,"d1":77,"r1":168,"s2":71,"d2":78,"r2":13,"label":""},{"lo":116.509,"la":-6.801,"de":531.1,"mw":5.6,"yr":2006,"ft":"N","s1":125,"d1":38,"r1":-106,"s2":325,"d2":53,"r2":-78,"label":""},{"lo":116.85,"la":-11.167,"de":24.2,"mw":5.9,"yr":2006,"ft":"N","s1":83,"d1":40,"r1":-102,"s2":278,"d2":51,"r2":-80,"label":""},{"lo":118.349,"la":-11.211,"de":34.2,"mw":5.8,"yr":2006,"ft":"N","s1":241,"d1":29,"r1":-109,"s2":82,"d2":62,"r2":-80,"label":""},{"lo":121.799,"la":1.281,"de":30.1,"mw":5.6,"yr":2006,"ft":"N","s1":264,"d1":27,"r1":-76,"s2":69,"d2":63,"r2":-97,"label":""},{"lo":123.107,"la":-5.119,"de":12.0,"mw":5.6,"yr":2006,"ft":"S","s1":210,"d1":42,"r1":156,"s2":318,"d2":75,"r2":51,"label":""},{"lo":124.83,"la":-0.179,"de":35.1,"mw":5.7,"yr":2006,"ft":"T","s1":238,"d1":34,"r1":82,"s2":67,"d2":56,"r2":96,"label":""},{"lo":124.944,"la":-0.177,"de":35.4,"mw":5.5,"yr":2006,"ft":"T","s1":246,"d1":30,"r1":119,"s2":34,"d2":64,"r2":74,"label":""},{"lo":125.061,"la":-0.267,"de":26.5,"mw":5.8,"yr":2006,"ft":"T","s1":213,"d1":26,"r1":54,"s2":72,"d2":69,"r2":106,"label":""},{"lo":125.072,"la":-7.471,"de":393.7,"mw":5.6,"yr":2006,"ft":"N","s1":89,"d1":44,"r1":-73,"s2":246,"d2":48,"r2":-106,"label":""},{"lo":125.123,"la":-0.348,"de":26.6,"mw":5.8,"yr":2006,"ft":"T","s1":223,"d1":33,"r1":56,"s2":81,"d2":63,"r2":110,"label":""},{"lo":125.222,"la":4.945,"de":12.1,"mw":5.7,"yr":2006,"ft":"T","s1":315,"d1":27,"r1":80,"s2":146,"d2":63,"r2":95,"label":""},{"lo":125.277,"la":3.269,"de":183.7,"mw":5.5,"yr":2006,"ft":"S","s1":358,"d1":55,"r1":39,"s2":242,"d2":59,"r2":138,"label":""},{"lo":125.375,"la":4.596,"de":186.7,"mw":5.7,"yr":2006,"ft":"S","s1":228,"d1":61,"r1":157,"s2":330,"d2":70,"r2":31,"label":""},{"lo":126.156,"la":-4.446,"de":385.1,"mw":5.8,"yr":2006,"ft":"N","s1":111,"d1":30,"r1":-62,"s2":259,"d2":64,"r2":-106,"label":""},{"lo":126.304,"la":1.454,"de":32.2,"mw":5.6,"yr":2006,"ft":"S","s1":62,"d1":48,"r1":142,"s2":179,"d2":63,"r2":49,"label":""},{"lo":126.407,"la":3.782,"de":20.0,"mw":5.6,"yr":2006,"ft":"T","s1":171,"d1":8,"r1":73,"s2":9,"d2":82,"r2":92,"label":""},{"lo":126.704,"la":-8.801,"de":14.7,"mw":5.7,"yr":2006,"ft":"T","s1":250,"d1":34,"r1":86,"s2":74,"d2":56,"r2":93,"label":""},{"lo":126.734,"la":-4.672,"de":12.0,"mw":5.9,"yr":2006,"ft":"T","s1":246,"d1":32,"r1":63,"s2":97,"d2":62,"r2":106,"label":""},{"lo":126.777,"la":2.324,"de":29.4,"mw":5.6,"yr":2006,"ft":"T","s1":6,"d1":42,"r1":101,"s2":171,"d2":49,"r2":80,"label":""},{"lo":126.791,"la":2.339,"de":32.4,"mw":5.5,"yr":2006,"ft":"T","s1":9,"d1":36,"r1":96,"s2":181,"d2":54,"r2":85,"label":""},{"lo":126.919,"la":0.85,"de":41.1,"mw":5.5,"yr":2006,"ft":"S","s1":138,"d1":74,"r1":-1,"s2":228,"d2":89,"r2":-164,"label":""},{"lo":127.736,"la":-7.147,"de":244.2,"mw":5.5,"yr":2006,"ft":"N","s1":280,"d1":5,"r1":-146,"s2":157,"d2":87,"r2":-86,"label":""},{"lo":116.811,"la":-8.285,"de":21.6,"mw":5.7,"yr":2007,"ft":"T","s1":96,"d1":32,"r1":112,"s2":250,"d2":60,"r2":77,"label":""},{"lo":117.006,"la":-10.378,"de":32.4,"mw":5.7,"yr":2007,"ft":"T","s1":277,"d1":30,"r1":81,"s2":107,"d2":60,"r2":95,"label":""},{"lo":117.863,"la":-8.128,"de":25.0,"mw":5.6,"yr":2007,"ft":"S","s1":140,"d1":44,"r1":-174,"s2":46,"d2":86,"r2":-46,"label":""},{"lo":118.797,"la":-9.553,"de":71.1,"mw":5.6,"yr":2007,"ft":"N","s1":39,"d1":36,"r1":-106,"s2":239,"d2":55,"r2":-78,"label":""},{"lo":122.631,"la":1.274,"de":26.4,"mw":5.6,"yr":2007,"ft":"T","s1":100,"d1":18,"r1":94,"s2":275,"d2":72,"r2":89,"label":""},{"lo":122.796,"la":-0.011,"de":172.8,"mw":5.5,"yr":2007,"ft":"T","s1":282,"d1":36,"r1":126,"s2":60,"d2":62,"r2":67,"label":""},{"lo":123.911,"la":6.636,"de":569.2,"mw":5.6,"yr":2007,"ft":"N","s1":121,"d1":10,"r1":-119,"s2":330,"d2":81,"r2":-85,"label":""},{"lo":124.189,"la":-0.438,"de":77.9,"mw":5.5,"yr":2007,"ft":"S","s1":149,"d1":40,"r1":22,"s2":42,"d2":76,"r2":128,"label":""},{"lo":125.763,"la":1.409,"de":71.2,"mw":5.5,"yr":2007,"ft":"T","s1":130,"d1":37,"r1":85,"s2":317,"d2":54,"r2":94,"label":""},{"lo":125.914,"la":0.831,"de":30.4,"mw":5.5,"yr":2007,"ft":"S","s1":75,"d1":74,"r1":-173,"s2":344,"d2":84,"r2":-16,"label":""},{"lo":125.971,"la":1.019,"de":13.3,"mw":5.6,"yr":2007,"ft":"T","s1":10,"d1":13,"r1":99,"s2":181,"d2":77,"r2":88,"label":""},{"lo":126.063,"la":1.216,"de":28.7,"mw":5.5,"yr":2007,"ft":"T","s1":212,"d1":42,"r1":112,"s2":4,"d2":51,"r2":71,"label":""},{"lo":126.17,"la":2.018,"de":96.5,"mw":5.6,"yr":2007,"ft":"S","s1":67,"d1":45,"r1":78,"s2":264,"d2":46,"r2":102,"label":""},{"lo":126.202,"la":1.282,"de":23.3,"mw":5.6,"yr":2007,"ft":"T","s1":22,"d1":35,"r1":101,"s2":188,"d2":56,"r2":82,"label":""},{"lo":126.238,"la":2.61,"de":47.8,"mw":5.6,"yr":2007,"ft":"S","s1":78,"d1":68,"r1":-175,"s2":346,"d2":85,"r2":-22,"label":""},{"lo":126.265,"la":1.024,"de":33.6,"mw":5.5,"yr":2007,"ft":"T","s1":23,"d1":33,"r1":88,"s2":206,"d2":57,"r2":92,"label":""},{"lo":126.312,"la":1.009,"de":21.0,"mw":5.8,"yr":2007,"ft":"T","s1":197,"d1":39,"r1":66,"s2":47,"d2":55,"r2":108,"label":""},{"lo":126.362,"la":1.545,"de":15.0,"mw":5.6,"yr":2007,"ft":"N","s1":267,"d1":2,"r1":-102,"s2":99,"d2":88,"r2":-90,"label":""},{"lo":126.413,"la":1.152,"de":31.7,"mw":5.7,"yr":2007,"ft":"S","s1":74,"d1":57,"r1":178,"s2":165,"d2":88,"r2":33,"label":""},{"lo":126.502,"la":1.218,"de":21.3,"mw":5.6,"yr":2007,"ft":"T","s1":211,"d1":29,"r1":113,"s2":4,"d2":63,"r2":78,"label":""},{"lo":126.563,"la":1.278,"de":23.6,"mw":5.5,"yr":2007,"ft":"T","s1":208,"d1":30,"r1":102,"s2":14,"d2":61,"r2":83,"label":""},{"lo":126.755,"la":4.174,"de":21.1,"mw":5.5,"yr":2007,"ft":"S","s1":170,"d1":46,"r1":52,"s2":38,"d2":56,"r2":122,"label":""},{"lo":126.806,"la":0.007,"de":22.5,"mw":5.9,"yr":2007,"ft":"T","s1":336,"d1":5,"r1":69,"s2":177,"d2":85,"r2":92,"label":""},{"lo":126.946,"la":2.505,"de":15.0,"mw":5.6,"yr":2007,"ft":"T","s1":224,"d1":11,"r1":123,"s2":10,"d2":81,"r2":84,"label":""},{"lo":126.956,"la":-1.132,"de":12.0,"mw":5.5,"yr":2007,"ft":"S","s1":16,"d1":57,"r1":-152,"s2":270,"d2":67,"r2":-37,"label":""},{"lo":127.117,"la":2.382,"de":15.4,"mw":5.6,"yr":2007,"ft":"T","s1":343,"d1":4,"r1":34,"s2":219,"d2":88,"r2":93,"label":""},{"lo":127.192,"la":-0.945,"de":20.2,"mw":5.5,"yr":2007,"ft":"S","s1":327,"d1":51,"r1":142,"s2":83,"d2":62,"r2":46,"label":""},{"lo":127.474,"la":5.977,"de":19.3,"mw":5.5,"yr":2007,"ft":"N","s1":150,"d1":33,"r1":-84,"s2":323,"d2":58,"r2":-94,"label":""},{"lo":127.936,"la":3.49,"de":88.7,"mw":5.6,"yr":2007,"ft":"T","s1":29,"d1":31,"r1":127,"s2":167,"d2":66,"r2":70,"label":""},{"lo":129.317,"la":-2.972,"de":16.0,"mw":5.5,"yr":2007,"ft":"T","s1":71,"d1":33,"r1":7,"s2":335,"d2":86,"r2":123,"label":""},{"lo":129.469,"la":-5.301,"de":16.9,"mw":5.8,"yr":2007,"ft":"S","s1":72,"d1":80,"r1":5,"s2":341,"d2":85,"r2":170,"label":""},{"lo":130.031,"la":-6.821,"de":129.3,"mw":5.7,"yr":2007,"ft":"T","s1":82,"d1":39,"r1":38,"s2":320,"d2":67,"r2":122,"label":""},{"lo":130.168,"la":-6.364,"de":149.9,"mw":5.6,"yr":2007,"ft":"T","s1":116,"d1":18,"r1":31,"s2":356,"d2":81,"r2":106,"label":""},{"lo":130.435,"la":-5.525,"de":146.4,"mw":5.7,"yr":2007,"ft":"S","s1":67,"d1":47,"r1":15,"s2":327,"d2":79,"r2":136,"label":""},{"lo":130.564,"la":-5.929,"de":142.4,"mw":5.9,"yr":2007,"ft":"S","s1":319,"d1":49,"r1":161,"s2":62,"d2":76,"r2":43,"label":""},{"lo":130.906,"la":-6.722,"de":102.6,"mw":5.8,"yr":2007,"ft":"S","s1":339,"d1":70,"r1":162,"s2":76,"d2":73,"r2":21,"label":""},{"lo":116.819,"la":-7.582,"de":320.7,"mw":5.7,"yr":2008,"ft":"S","s1":132,"d1":42,"r1":19,"s2":28,"d2":78,"r2":130,"label":""},{"lo":117.665,"la":-8.131,"de":27.0,"mw":5.9,"yr":2008,"ft":"S","s1":130,"d1":76,"r1":-171,"s2":38,"d2":81,"r2":-14,"label":""},{"lo":118.07,"la":-3.517,"de":18.8,"mw":5.9,"yr":2008,"ft":"S","s1":28,"d1":51,"r1":51,"s2":261,"d2":53,"r2":128,"label":""},{"lo":120.255,"la":-8.166,"de":20.6,"mw":5.9,"yr":2008,"ft":"T","s1":93,"d1":26,"r1":100,"s2":261,"d2":64,"r2":85,"label":""},{"lo":120.265,"la":-8.125,"de":18.0,"mw":5.8,"yr":2008,"ft":"T","s1":88,"d1":23,"r1":93,"s2":265,"d2":67,"r2":89,"label":""},{"lo":120.681,"la":0.109,"de":108.4,"mw":5.9,"yr":2008,"ft":"T","s1":314,"d1":35,"r1":35,"s2":194,"d2":71,"r2":120,"label":""},{"lo":122.653,"la":1.228,"de":30.6,"mw":5.8,"yr":2008,"ft":"T","s1":98,"d1":21,"r1":96,"s2":271,"d2":69,"r2":88,"label":""},{"lo":123.015,"la":-0.141,"de":74.1,"mw":5.6,"yr":2008,"ft":"S","s1":207,"d1":44,"r1":36,"s2":90,"d2":66,"r2":128,"label":""},{"lo":123.433,"la":0.063,"de":134.9,"mw":5.9,"yr":2008,"ft":"T","s1":323,"d1":18,"r1":144,"s2":87,"d2":80,"r2":75,"label":""},{"lo":125.083,"la":-0.169,"de":42.0,"mw":5.5,"yr":2008,"ft":"T","s1":244,"d1":33,"r1":119,"s2":30,"d2":61,"r2":72,"label":""},{"lo":125.685,"la":-7.85,"de":12.0,"mw":5.6,"yr":2008,"ft":"T","s1":51,"d1":28,"r1":90,"s2":231,"d2":62,"r2":90,"label":""},{"lo":125.778,"la":5.957,"de":126.7,"mw":5.7,"yr":2008,"ft":"T","s1":152,"d1":26,"r1":46,"s2":19,"d2":72,"r2":109,"label":""},{"lo":126.041,"la":4.538,"de":113.9,"mw":5.6,"yr":2008,"ft":"N","s1":17,"d1":15,"r1":-46,"s2":152,"d2":79,"r2":-100,"label":""},{"lo":126.081,"la":0.829,"de":31.9,"mw":5.7,"yr":2008,"ft":"S","s1":63,"d1":66,"r1":154,"s2":165,"d2":67,"r2":27,"label":""},{"lo":126.844,"la":-8.779,"de":17.6,"mw":5.7,"yr":2008,"ft":"T","s1":251,"d1":27,"r1":92,"s2":68,"d2":63,"r2":89,"label":""},{"lo":126.855,"la":-8.728,"de":23.1,"mw":5.6,"yr":2008,"ft":"T","s1":265,"d1":27,"r1":117,"s2":55,"d2":66,"r2":77,"label":""},{"lo":127.484,"la":-6.108,"de":412.2,"mw":5.9,"yr":2008,"ft":"S","s1":13,"d1":36,"r1":4,"s2":280,"d2":88,"r2":126,"label":""},{"lo":127.732,"la":-7.47,"de":151.5,"mw":5.6,"yr":2008,"ft":"T","s1":66,"d1":28,"r1":58,"s2":281,"d2":66,"r2":106,"label":""},{"lo":128.232,"la":2.572,"de":131.4,"mw":5.9,"yr":2008,"ft":"T","s1":148,"d1":34,"r1":44,"s2":19,"d2":67,"r2":116,"label":""},{"lo":128.799,"la":-5.659,"de":315.0,"mw":5.6,"yr":2008,"ft":"N","s1":283,"d1":12,"r1":-126,"s2":139,"d2":80,"r2":-83,"label":""},{"lo":128.956,"la":-3.78,"de":108.8,"mw":5.6,"yr":2008,"ft":"S","s1":311,"d1":57,"r1":18,"s2":211,"d2":75,"r2":146,"label":""},{"lo":129.203,"la":-7.046,"de":190.0,"mw":5.7,"yr":2008,"ft":"S","s1":288,"d1":62,"r1":151,"s2":33,"d2":64,"r2":32,"label":""},{"lo":129.227,"la":-6.676,"de":20.7,"mw":5.8,"yr":2008,"ft":"S","s1":55,"d1":73,"r1":4,"s2":324,"d2":86,"r2":163,"label":""},{"lo":129.483,"la":-7.061,"de":133.2,"mw":5.7,"yr":2008,"ft":"S","s1":121,"d1":51,"r1":4,"s2":29,"d2":87,"r2":141,"label":""},{"lo":129.65,"la":-6.132,"de":19.6,"mw":5.8,"yr":2008,"ft":"S","s1":60,"d1":73,"r1":11,"s2":326,"d2":79,"r2":163,"label":""},{"lo":131.368,"la":-3.913,"de":14.2,"mw":5.8,"yr":2008,"ft":"T","s1":169,"d1":19,"r1":102,"s2":336,"d2":71,"r2":86,"label":""},{"lo":131.446,"la":-3.86,"de":14.3,"mw":5.5,"yr":2008,"ft":"T","s1":155,"d1":23,"r1":84,"s2":342,"d2":67,"r2":93,"label":""},{"lo":115.593,"la":-9.138,"de":70.1,"mw":5.7,"yr":2009,"ft":"T","s1":18,"d1":42,"r1":62,"s2":234,"d2":54,"r2":114,"label":""},{"lo":117.2,"la":-7.686,"de":27.9,"mw":5.5,"yr":2009,"ft":"T","s1":271,"d1":37,"r1":93,"s2":87,"d2":53,"r2":88,"label":""},{"lo":118.793,"la":-9.896,"de":33.8,"mw":5.6,"yr":2009,"ft":"T","s1":265,"d1":24,"r1":100,"s2":74,"d2":66,"r2":85,"label":""},{"lo":119.32,"la":-9.139,"de":72.4,"mw":5.9,"yr":2009,"ft":"N","s1":214,"d1":34,"r1":-152,"s2":100,"d2":75,"r2":-59,"label":""},{"lo":119.868,"la":-1.105,"de":12.9,"mw":5.6,"yr":2009,"ft":"N","s1":125,"d1":40,"r1":-93,"s2":309,"d2":50,"r2":-87,"label":""},{"lo":120.897,"la":1.118,"de":40.3,"mw":5.8,"yr":2009,"ft":"T","s1":78,"d1":22,"r1":86,"s2":262,"d2":68,"r2":92,"label":""},{"lo":122.204,"la":1.381,"de":26.4,"mw":5.7,"yr":2009,"ft":"T","s1":95,"d1":16,"r1":96,"s2":270,"d2":74,"r2":88,"label":""},{"lo":123.16,"la":-3.615,"de":12.0,"mw":5.7,"yr":2009,"ft":"N","s1":87,"d1":41,"r1":-69,"s2":240,"d2":52,"r2":-107,"label":""},{"lo":123.203,"la":-3.651,"de":12.0,"mw":5.6,"yr":2009,"ft":"S","s1":84,"d1":50,"r1":-55,"s2":217,"d2":51,"r2":-124,"label":""},{"lo":123.247,"la":-3.629,"de":12.0,"mw":5.5,"yr":2009,"ft":"N","s1":72,"d1":38,"r1":-89,"s2":250,"d2":52,"r2":-91,"label":""},{"lo":123.661,"la":-10.028,"de":35.5,"mw":5.5,"yr":2009,"ft":"S","s1":83,"d1":44,"r1":-43,"s2":207,"d2":62,"r2":-125,"label":""},{"lo":124.157,"la":-8.936,"de":90.9,"mw":5.7,"yr":2009,"ft":"N","s1":112,"d1":25,"r1":-1,"s2":203,"d2":90,"r2":-115,"label":""},{"lo":124.715,"la":6.513,"de":15.7,"mw":5.7,"yr":2009,"ft":"S","s1":61,"d1":75,"r1":-167,"s2":328,"d2":78,"r2":-15,"label":""},{"lo":125.093,"la":-6.822,"de":554.7,"mw":5.6,"yr":2009,"ft":"S","s1":138,"d1":40,"r1":-158,"s2":31,"d2":76,"r2":-53,"label":""},{"lo":125.676,"la":-6.813,"de":535.3,"mw":5.7,"yr":2009,"ft":"S","s1":170,"d1":45,"r1":-78,"s2":334,"d2":47,"r2":-101,"label":""},{"lo":125.776,"la":5.927,"de":146.9,"mw":5.7,"yr":2009,"ft":"S","s1":244,"d1":52,"r1":170,"s2":340,"d2":82,"r2":39,"label":""},{"lo":125.963,"la":1.052,"de":29.8,"mw":5.8,"yr":2009,"ft":"T","s1":16,"d1":28,"r1":98,"s2":187,"d2":62,"r2":86,"label":""},{"lo":126.012,"la":2.408,"de":107.7,"mw":5.7,"yr":2009,"ft":"S","s1":293,"d1":52,"r1":177,"s2":25,"d2":88,"r2":38,"label":""},{"lo":126.083,"la":0.415,"de":32.5,"mw":5.5,"yr":2009,"ft":"T","s1":9,"d1":40,"r1":56,"s2":230,"d2":58,"r2":115,"label":""},{"lo":126.254,"la":5.345,"de":35.5,"mw":5.7,"yr":2009,"ft":"T","s1":180,"d1":25,"r1":90,"s2":360,"d2":65,"r2":90,"label":""},{"lo":126.341,"la":6.52,"de":33.4,"mw":5.5,"yr":2009,"ft":"T","s1":165,"d1":30,"r1":78,"s2":359,"d2":61,"r2":97,"label":""},{"lo":126.369,"la":6.482,"de":32.7,"mw":5.6,"yr":2009,"ft":"T","s1":177,"d1":28,"r1":84,"s2":4,"d2":62,"r2":93,"label":""},{"lo":126.376,"la":6.04,"de":94.1,"mw":5.7,"yr":2009,"ft":"T","s1":240,"d1":36,"r1":162,"s2":344,"d2":80,"r2":55,"label":""},{"lo":126.483,"la":3.979,"de":25.0,"mw":5.7,"yr":2009,"ft":"T","s1":146,"d1":26,"r1":37,"s2":22,"d2":75,"r2":111,"label":""},{"lo":126.511,"la":5.008,"de":20.0,"mw":5.6,"yr":2009,"ft":"S","s1":79,"d1":69,"r1":-162,"s2":342,"d2":73,"r2":-22,"label":""},{"lo":126.65,"la":3.715,"de":24.3,"mw":5.9,"yr":2009,"ft":"T","s1":142,"d1":40,"r1":39,"s2":21,"d2":66,"r2":123,"label":""},{"lo":126.655,"la":3.648,"de":23.5,"mw":5.5,"yr":2009,"ft":"S","s1":164,"d1":46,"r1":36,"s2":47,"d2":65,"r2":131,"label":""},{"lo":126.683,"la":3.754,"de":20.0,"mw":5.6,"yr":2009,"ft":"S","s1":156,"d1":62,"r1":9,"s2":62,"d2":82,"r2":151,"label":""},{"lo":126.7,"la":3.597,"de":13.0,"mw":5.7,"yr":2009,"ft":"T","s1":24,"d1":26,"r1":134,"s2":158,"d2":71,"r2":71,"label":""},{"lo":126.793,"la":3.706,"de":12.0,"mw":5.6,"yr":2009,"ft":"T","s1":168,"d1":31,"r1":67,"s2":14,"d2":62,"r2":103,"label":""},{"lo":126.798,"la":4.042,"de":22.1,"mw":5.6,"yr":2009,"ft":"T","s1":177,"d1":40,"r1":86,"s2":2,"d2":50,"r2":93,"label":""},{"lo":126.815,"la":4.416,"de":26.1,"mw":5.5,"yr":2009,"ft":"T","s1":263,"d1":7,"r1":180,"s2":353,"d2":90,"r2":83,"label":""},{"lo":126.931,"la":4.431,"de":24.7,"mw":5.7,"yr":2009,"ft":"T","s1":238,"d1":4,"r1":141,"s2":7,"d2":88,"r2":87,"label":""},{"lo":126.94,"la":2.301,"de":25.4,"mw":5.5,"yr":2009,"ft":"T","s1":15,"d1":44,"r1":93,"s2":190,"d2":46,"r2":87,"label":""},{"lo":127.077,"la":2.483,"de":45.3,"mw":5.5,"yr":2009,"ft":"T","s1":80,"d1":28,"r1":117,"s2":230,"d2":65,"r2":76,"label":""},{"lo":127.189,"la":1.755,"de":117.2,"mw":5.8,"yr":2009,"ft":"N","s1":234,"d1":14,"r1":-115,"s2":80,"d2":77,"r2":-84,"label":""},{"lo":127.772,"la":-7.467,"de":160.3,"mw":5.5,"yr":2009,"ft":"T","s1":23,"d1":28,"r1":53,"s2":243,"d2":68,"r2":108,"label":""},{"lo":129.664,"la":-4.23,"de":12.0,"mw":5.7,"yr":2009,"ft":"S","s1":295,"d1":51,"r1":48,"s2":169,"d2":55,"r2":129,"label":""},{"lo":129.729,"la":-4.168,"de":12.0,"mw":5.6,"yr":2009,"ft":"T","s1":315,"d1":40,"r1":97,"s2":126,"d2":51,"r2":84,"label":""},{"lo":129.814,"la":-4.667,"de":164.1,"mw":5.5,"yr":2009,"ft":"T","s1":119,"d1":26,"r1":15,"s2":16,"d2":84,"r2":116,"label":""},{"lo":130.217,"la":-6.372,"de":124.7,"mw":5.6,"yr":2009,"ft":"S","s1":307,"d1":53,"r1":148,"s2":58,"d2":65,"r2":41,"label":""},{"lo":130.229,"la":-8.01,"de":20.8,"mw":5.6,"yr":2009,"ft":"T","s1":270,"d1":24,"r1":100,"s2":79,"d2":67,"r2":85,"label":""},{"lo":118.259,"la":-8.085,"de":20.0,"mw":5.9,"yr":2010,"ft":"T","s1":77,"d1":24,"r1":88,"s2":258,"d2":65,"r2":90,"label":""},{"lo":119.951,"la":-7.999,"de":197.8,"mw":5.5,"yr":2010,"ft":"N","s1":242,"d1":15,"r1":-126,"s2":99,"d2":78,"r2":-81,"label":""},{"lo":122.485,"la":-0.732,"de":12.0,"mw":5.7,"yr":2010,"ft":"N","s1":128,"d1":39,"r1":-62,"s2":273,"d2":56,"r2":-111,"label":""},{"lo":124.657,"la":0.511,"de":133.8,"mw":5.8,"yr":2010,"ft":"N","s1":153,"d1":36,"r1":-11,"s2":251,"d2":84,"r2":-125,"label":""},{"lo":125.059,"la":-0.071,"de":37.5,"mw":5.8,"yr":2010,"ft":"T","s1":236,"d1":29,"r1":108,"s2":35,"d2":63,"r2":80,"label":""},{"lo":125.699,"la":-7.366,"de":21.0,"mw":5.9,"yr":2010,"ft":"T","s1":283,"d1":39,"r1":98,"s2":92,"d2":50,"r2":82,"label":""},{"lo":126.393,"la":-7.318,"de":377.2,"mw":5.5,"yr":2010,"ft":"S","s1":112,"d1":62,"r1":-30,"s2":217,"d2":63,"r2":-149,"label":""},{"lo":126.583,"la":2.094,"de":33.4,"mw":5.5,"yr":2010,"ft":"T","s1":4,"d1":39,"r1":70,"s2":209,"d2":54,"r2":106,"label":""},{"lo":126.802,"la":6.484,"de":111.0,"mw":5.7,"yr":2010,"ft":"T","s1":141,"d1":19,"r1":47,"s2":6,"d2":75,"r2":103,"label":""},{"lo":127.982,"la":3.559,"de":114.6,"mw":5.6,"yr":2010,"ft":"S","s1":157,"d1":45,"r1":75,"s2":357,"d2":47,"r2":104,"label":""},{"lo":128.071,"la":3.862,"de":70.8,"mw":5.7,"yr":2010,"ft":"S","s1":36,"d1":42,"r1":4,"s2":303,"d2":87,"r2":132,"label":""},{"lo":128.751,"la":-6.559,"de":243.3,"mw":5.5,"yr":2010,"ft":"S","s1":175,"d1":54,"r1":-165,"s2":76,"d2":78,"r2":-37,"label":""},{"lo":129.029,"la":-8.205,"de":22.0,"mw":5.5,"yr":2010,"ft":"T","s1":239,"d1":41,"r1":85,"s2":66,"d2":49,"r2":95,"label":""},{"lo":129.24,"la":-1.068,"de":12.5,"mw":5.8,"yr":2010,"ft":"S","s1":98,"d1":80,"r1":6,"s2":7,"d2":84,"r2":170,"label":""},{"lo":129.385,"la":-5.171,"de":21.6,"mw":5.8,"yr":2010,"ft":"S","s1":74,"d1":64,"r1":23,"s2":334,"d2":69,"r2":152,"label":""},{"lo":129.446,"la":-7.797,"de":35.0,"mw":5.9,"yr":2010,"ft":"T","s1":273,"d1":40,"r1":108,"s2":70,"d2":52,"r2":75,"label":""},{"lo":129.898,"la":-6.686,"de":171.1,"mw":5.5,"yr":2010,"ft":"S","s1":303,"d1":41,"r1":168,"s2":42,"d2":82,"r2":49,"label":""},{"lo":129.996,"la":-6.48,"de":170.1,"mw":5.5,"yr":2010,"ft":"N","s1":315,"d1":28,"r1":-150,"s2":198,"d2":76,"r2":-65,"label":""},{"lo":130.035,"la":-6.553,"de":172.6,"mw":5.5,"yr":2010,"ft":"N","s1":329,"d1":23,"r1":-119,"s2":180,"d2":70,"r2":-78,"label":""},{"lo":130.284,"la":-6.326,"de":123.0,"mw":5.7,"yr":2010,"ft":"S","s1":294,"d1":53,"r1":135,"s2":54,"d2":55,"r2":46,"label":""},{"lo":131.014,"la":-3.369,"de":21.0,"mw":5.8,"yr":2010,"ft":"T","s1":128,"d1":23,"r1":70,"s2":330,"d2":67,"r2":98,"label":""},{"lo":116.983,"la":-7.019,"de":630.0,"mw":5.8,"yr":2011,"ft":"N","s1":50,"d1":42,"r1":-119,"s2":267,"d2":54,"r2":-65,"label":""},{"lo":119.638,"la":-1.265,"de":11.0,"mw":5.7,"yr":2011,"ft":"T","s1":9,"d1":17,"r1":58,"s2":222,"d2":76,"r2":99,"label":""},{"lo":120.499,"la":0.121,"de":91.7,"mw":5.5,"yr":2011,"ft":"S","s1":300,"d1":42,"r1":26,"s2":189,"d2":73,"r2":129,"label":""},{"lo":121.694,"la":-4.061,"de":12.3,"mw":5.5,"yr":2011,"ft":"S","s1":131,"d1":45,"r1":-79,"s2":296,"d2":46,"r2":-100,"label":""},{"lo":121.914,"la":-0.095,"de":270.0,"mw":5.7,"yr":2011,"ft":"N","s1":78,"d1":31,"r1":-76,"s2":242,"d2":59,"r2":-98,"label":""},{"lo":121.974,"la":-0.626,"de":17.0,"mw":5.5,"yr":2011,"ft":"S","s1":10,"d1":51,"r1":-28,"s2":119,"d2":68,"r2":-137,"label":""},{"lo":122.471,"la":-8.926,"de":130.0,"mw":5.5,"yr":2011,"ft":"T","s1":316,"d1":25,"r1":164,"s2":60,"d2":84,"r2":66,"label":""},{"lo":122.948,"la":-0.065,"de":85.0,"mw":5.5,"yr":2011,"ft":"T","s1":44,"d1":34,"r1":112,"s2":198,"d2":59,"r2":76,"label":""},{"lo":124.913,"la":-0.026,"de":45.2,"mw":5.6,"yr":2011,"ft":"T","s1":239,"d1":32,"r1":113,"s2":33,"d2":61,"r2":77,"label":""},{"lo":126.415,"la":5.343,"de":31.9,"mw":5.7,"yr":2011,"ft":"T","s1":177,"d1":34,"r1":81,"s2":8,"d2":57,"r2":96,"label":""},{"lo":126.514,"la":-1.439,"de":25.0,"mw":5.8,"yr":2011,"ft":"S","s1":357,"d1":43,"r1":-54,"s2":132,"d2":56,"r2":-118,"label":""},{"lo":126.833,"la":1.993,"de":24.4,"mw":5.6,"yr":2011,"ft":"S","s1":340,"d1":43,"r1":32,"s2":226,"d2":69,"r2":129,"label":""},{"lo":126.94,"la":3.029,"de":17.0,"mw":5.9,"yr":2011,"ft":"T","s1":203,"d1":14,"r1":87,"s2":26,"d2":76,"r2":91,"label":""},{"lo":127.585,"la":-7.089,"de":270.0,"mw":5.9,"yr":2011,"ft":"T","s1":74,"d1":25,"r1":20,"s2":326,"d2":82,"r2":113,"label":""},{"lo":127.849,"la":-7.482,"de":160.0,"mw":5.5,"yr":2011,"ft":"T","s1":313,"d1":21,"r1":158,"s2":63,"d2":82,"r2":70,"label":""},{"lo":129.396,"la":-4.137,"de":15.1,"mw":5.5,"yr":2011,"ft":"T","s1":294,"d1":38,"r1":97,"s2":106,"d2":53,"r2":85,"label":""},{"lo":130.252,"la":-5.65,"de":195.9,"mw":5.7,"yr":2011,"ft":"N","s1":283,"d1":22,"r1":-121,"s2":136,"d2":71,"r2":-78,"label":""},{"lo":130.492,"la":-6.055,"de":126.0,"mw":5.6,"yr":2011,"ft":"T","s1":93,"d1":14,"r1":18,"s2":346,"d2":85,"r2":103,"label":""},{"lo":119.701,"la":-8.406,"de":130.0,"mw":5.7,"yr":2012,"ft":"S","s1":35,"d1":64,"r1":7,"s2":302,"d2":84,"r2":154,"label":""},{"lo":121.855,"la":-2.64,"de":11.0,"mw":5.8,"yr":2012,"ft":"S","s1":118,"d1":54,"r1":4,"s2":25,"d2":86,"r2":144,"label":""},{"lo":122.167,"la":1.357,"de":17.0,"mw":5.6,"yr":2012,"ft":"T","s1":125,"d1":22,"r1":122,"s2":272,"d2":71,"r2":78,"label":""},{"lo":122.2,"la":1.374,"de":17.0,"mw":5.7,"yr":2012,"ft":"T","s1":96,"d1":18,"r1":100,"s2":266,"d2":72,"r2":87,"label":""},{"lo":122.918,"la":-0.145,"de":120.0,"mw":5.5,"yr":2012,"ft":"T","s1":243,"d1":22,"r1":49,"s2":106,"d2":74,"r2":105,"label":""},{"lo":123.465,"la":-8.185,"de":12.3,"mw":5.5,"yr":2012,"ft":"S","s1":76,"d1":59,"r1":-179,"s2":346,"d2":89,"r2":-31,"label":""},{"lo":123.875,"la":6.61,"de":17.0,"mw":5.8,"yr":2012,"ft":"T","s1":358,"d1":21,"r1":80,"s2":189,"d2":69,"r2":94,"label":""},{"lo":125.185,"la":-0.142,"de":23.0,"mw":5.7,"yr":2012,"ft":"T","s1":265,"d1":31,"r1":139,"s2":31,"d2":70,"r2":65,"label":""},{"lo":125.293,"la":0.374,"de":60.0,"mw":5.7,"yr":2012,"ft":"T","s1":248,"d1":19,"r1":121,"s2":35,"d2":74,"r2":80,"label":""},{"lo":126.166,"la":6.703,"de":49.5,"mw":5.6,"yr":2012,"ft":"T","s1":272,"d1":28,"r1":-180,"s2":182,"d2":90,"r2":-62,"label":""},{"lo":126.354,"la":5.719,"de":50.0,"mw":5.7,"yr":2012,"ft":"T","s1":243,"d1":33,"r1":142,"s2":6,"d2":70,"r2":63,"label":""},{"lo":126.828,"la":1.293,"de":80.0,"mw":5.5,"yr":2012,"ft":"T","s1":182,"d1":18,"r1":45,"s2":49,"d2":78,"r2":103,"label":""},{"lo":126.829,"la":-0.877,"de":15.0,"mw":5.8,"yr":2012,"ft":"N","s1":291,"d1":13,"r1":-26,"s2":47,"d2":84,"r2":-101,"label":""},{"lo":126.853,"la":-0.978,"de":18.8,"mw":5.5,"yr":2012,"ft":"S","s1":13,"d1":52,"r1":-150,"s2":264,"d2":67,"r2":-42,"label":""},{"lo":128.511,"la":-5.689,"de":367.8,"mw":5.5,"yr":2012,"ft":"S","s1":96,"d1":55,"r1":0,"s2":186,"d2":90,"r2":-145,"label":""},{"lo":128.697,"la":2.645,"de":25.0,"mw":5.8,"yr":2012,"ft":"N","s1":150,"d1":18,"r1":-67,"s2":306,"d2":73,"r2":-97,"label":""},{"lo":129.219,"la":-2.952,"de":21.0,"mw":5.7,"yr":2012,"ft":"S","s1":80,"d1":54,"r1":28,"s2":333,"d2":68,"r2":140,"label":""},{"lo":129.321,"la":-2.885,"de":23.5,"mw":5.5,"yr":2012,"ft":"S","s1":62,"d1":73,"r1":6,"s2":331,"d2":85,"r2":163,"label":""},{"lo":131.121,"la":-6.944,"de":78.4,"mw":5.5,"yr":2012,"ft":"S","s1":67,"d1":78,"r1":5,"s2":336,"d2":85,"r2":168,"label":""},{"lo":131.134,"la":-5.398,"de":70.0,"mw":5.6,"yr":2012,"ft":"S","s1":287,"d1":42,"r1":144,"s2":46,"d2":67,"r2":54,"label":""},{"lo":120.278,"la":-9.353,"de":88.4,"mw":5.5,"yr":2013,"ft":"N","s1":38,"d1":19,"r1":-103,"s2":232,"d2":71,"r2":-85,"label":""},{"lo":121.632,"la":-11.976,"de":35.0,"mw":5.8,"yr":2013,"ft":"N","s1":323,"d1":26,"r1":-8,"s2":61,"d2":86,"r2":-115,"label":""},{"lo":122.211,"la":0.745,"de":95.6,"mw":5.5,"yr":2013,"ft":"T","s1":307,"d1":86,"r1":101,"s2":57,"d2":12,"r2":20,"label":""},{"lo":122.224,"la":1.381,"de":21.0,"mw":5.6,"yr":2013,"ft":"T","s1":115,"d1":27,"r1":109,"s2":273,"d2":64,"r2":80,"label":""},{"lo":123.347,"la":4.657,"de":550.0,"mw":5.9,"yr":2013,"ft":"N","s1":280,"d1":21,"r1":-26,"s2":35,"d2":81,"r2":-108,"label":""},{"lo":125.054,"la":-0.141,"de":35.0,"mw":5.5,"yr":2013,"ft":"T","s1":263,"d1":29,"r1":132,"s2":37,"d2":68,"r2":69,"label":""},{"lo":126.175,"la":6.624,"de":48.0,"mw":5.6,"yr":2013,"ft":"S","s1":62,"d1":62,"r1":142,"s2":173,"d2":57,"r2":34,"label":""},{"lo":126.246,"la":1.3,"de":35.5,"mw":5.7,"yr":2013,"ft":"T","s1":206,"d1":30,"r1":81,"s2":35,"d2":60,"r2":95,"label":""},{"lo":127.13,"la":1.114,"de":140.0,"mw":5.7,"yr":2013,"ft":"S","s1":314,"d1":37,"r1":-2,"s2":46,"d2":89,"r2":-126,"label":""},{"lo":127.386,"la":-1.564,"de":16.0,"mw":5.6,"yr":2013,"ft":"S","s1":353,"d1":82,"r1":166,"s2":85,"d2":76,"r2":8,"label":""},{"lo":127.467,"la":-8.467,"de":25.0,"mw":5.9,"yr":2013,"ft":"T","s1":247,"d1":19,"r1":98,"s2":59,"d2":71,"r2":87,"label":""},{"lo":127.916,"la":-7.51,"de":117.1,"mw":5.5,"yr":2013,"ft":"T","s1":324,"d1":38,"r1":112,"s2":118,"d2":55,"r2":74,"label":""},{"lo":128.323,"la":-6.908,"de":12.0,"mw":5.7,"yr":2013,"ft":"S","s1":223,"d1":72,"r1":31,"s2":122,"d2":61,"r2":159,"label":""},{"lo":130.218,"la":-6.292,"de":120.0,"mw":5.9,"yr":2013,"ft":"S","s1":65,"d1":69,"r1":6,"s2":333,"d2":84,"r2":159,"label":""},{"lo":117.589,"la":-6.988,"de":560.5,"mw":5.7,"yr":2014,"ft":"N","s1":315,"d1":67,"r1":-61,"s2":80,"d2":36,"r2":-139,"label":""},{"lo":120.315,"la":-7.104,"de":598.7,"mw":5.5,"yr":2014,"ft":"N","s1":93,"d1":54,"r1":-103,"s2":295,"d2":38,"r2":-73,"label":""},{"lo":122.423,"la":-2.932,"de":19.9,"mw":5.5,"yr":2014,"ft":"S","s1":38,"d1":87,"r1":160,"s2":129,"d2":70,"r2":3,"label":""},{"lo":122.935,"la":4.516,"de":572.9,"mw":5.8,"yr":2014,"ft":"N","s1":22,"d1":83,"r1":-106,"s2":270,"d2":17,"r2":-23,"label":""},{"lo":123.889,"la":-0.145,"de":90.5,"mw":5.9,"yr":2014,"ft":"S","s1":99,"d1":72,"r1":19,"s2":3,"d2":72,"r2":161,"label":""},{"lo":124.528,"la":-8.208,"de":16.4,"mw":5.5,"yr":2014,"ft":"T","s1":237,"d1":67,"r1":78,"s2":86,"d2":26,"r2":116,"label":""},{"lo":125.125,"la":-0.183,"de":30.5,"mw":5.9,"yr":2014,"ft":"T","s1":33,"d1":72,"r1":78,"s2":248,"d2":21,"r2":123,"label":""},{"lo":126.232,"la":1.538,"de":35.5,"mw":5.7,"yr":2014,"ft":"S","s1":51,"d1":56,"r1":132,"s2":173,"d2":52,"r2":46,"label":""},{"lo":126.475,"la":1.869,"de":30.5,"mw":5.8,"yr":2014,"ft":"T","s1":78,"d1":76,"r1":94,"s2":243,"d2":14,"r2":75,"label":""},{"lo":126.563,"la":1.786,"de":23.5,"mw":5.5,"yr":2014,"ft":"T","s1":220,"d1":56,"r1":99,"s2":23,"d2":36,"r2":76,"label":""},{"lo":127.008,"la":2.384,"de":25.5,"mw":5.8,"yr":2014,"ft":"T","s1":343,"d1":63,"r1":81,"s2":182,"d2":28,"r2":106,"label":""},{"lo":127.135,"la":5.869,"de":91.7,"mw":5.6,"yr":2014,"ft":"T","s1":14,"d1":66,"r1":93,"s2":187,"d2":24,"r2":84,"label":""},{"lo":127.401,"la":-3.815,"de":30.5,"mw":5.7,"yr":2014,"ft":"S","s1":266,"d1":55,"r1":55,"s2":137,"d2":48,"r2":129,"label":""},{"lo":128.172,"la":-7.192,"de":21.5,"mw":5.8,"yr":2014,"ft":"S","s1":98,"d1":46,"r1":107,"s2":254,"d2":46,"r2":73,"label":""},{"lo":119.37,"la":-2.432,"de":16.1,"mw":5.6,"yr":2015,"ft":"S","s1":314,"d1":81,"r1":-33,"s2":50,"d2":57,"r2":-169,"label":""},{"lo":119.757,"la":4.608,"de":17.5,"mw":5.5,"yr":2015,"ft":"T","s1":340,"d1":51,"r1":77,"s2":179,"d2":40,"r2":105,"label":""},{"lo":119.84,"la":6.082,"de":25.5,"mw":5.7,"yr":2015,"ft":"S","s1":338,"d1":86,"r1":-24,"s2":70,"d2":66,"r2":-175,"label":""},{"lo":121.99,"la":0.4,"de":130.5,"mw":5.9,"yr":2015,"ft":"T","s1":265,"d1":68,"r1":104,"s2":51,"d2":26,"r2":59,"label":""},{"lo":123.797,"la":5.265,"de":515.0,"mw":5.5,"yr":2015,"ft":"S","s1":119,"d1":38,"r1":173,"s2":214,"d2":86,"r2":53,"label":""},{"lo":124.47,"la":0.024,"de":65.0,"mw":5.6,"yr":2015,"ft":"T","s1":321,"d1":60,"r1":75,"s2":169,"d2":33,"r2":114,"label":""},{"lo":124.631,"la":4.413,"de":310.5,"mw":5.7,"yr":2015,"ft":"S","s1":40,"d1":71,"r1":-48,"s2":151,"d2":44,"r2":-152,"label":""},{"lo":124.907,"la":-8.283,"de":19.5,"mw":5.7,"yr":2015,"ft":"S","s1":13,"d1":70,"r1":-23,"s2":111,"d2":68,"r2":-158,"label":""},{"lo":125.252,"la":-9.742,"de":23.5,"mw":5.8,"yr":2015,"ft":"T","s1":68,"d1":65,"r1":88,"s2":252,"d2":25,"r2":94,"label":""},{"lo":125.845,"la":4.154,"de":140.5,"mw":5.7,"yr":2015,"ft":"T","s1":327,"d1":85,"r1":62,"s2":228,"d2":28,"r2":170,"label":""},{"lo":126.29,"la":1.431,"de":40.5,"mw":5.7,"yr":2015,"ft":"S","s1":9,"d1":46,"r1":75,"s2":210,"d2":45,"r2":105,"label":""},{"lo":126.485,"la":1.653,"de":45.5,"mw":5.6,"yr":2015,"ft":"S","s1":204,"d1":48,"r1":109,"s2":357,"d2":46,"r2":70,"label":""},{"lo":126.589,"la":0.485,"de":45.5,"mw":5.8,"yr":2015,"ft":"T","s1":223,"d1":69,"r1":100,"s2":17,"d2":23,"r2":67,"label":""},{"lo":126.682,"la":2.055,"de":45.5,"mw":5.5,"yr":2015,"ft":"T","s1":192,"d1":54,"r1":90,"s2":12,"d2":35,"r2":90,"label":""},{"lo":126.695,"la":2.117,"de":35.5,"mw":5.5,"yr":2015,"ft":"T","s1":199,"d1":53,"r1":82,"s2":32,"d2":37,"r2":100,"label":""},{"lo":128.187,"la":2.992,"de":127.0,"mw":5.5,"yr":2015,"ft":"S","s1":25,"d1":79,"r1":160,"s2":119,"d2":71,"r2":12,"label":""},{"lo":128.93,"la":-7.249,"de":140.5,"mw":5.8,"yr":2015,"ft":"S","s1":78,"d1":57,"r1":49,"s2":316,"d2":50,"r2":135,"label":""},{"lo":128.977,"la":-7.218,"de":140.5,"mw":5.8,"yr":2015,"ft":"T","s1":323,"d1":59,"r1":112,"s2":105,"d2":38,"r2":58,"label":""},{"lo":129.605,"la":-7.177,"de":130.5,"mw":5.5,"yr":2015,"ft":"T","s1":57,"d1":76,"r1":87,"s2":251,"d2":14,"r2":104,"label":""},{"lo":131.863,"la":-5.773,"de":80.5,"mw":5.5,"yr":2015,"ft":"S","s1":330,"d1":84,"r1":153,"s2":63,"d2":63,"r2":7,"label":""},{"lo":117.814,"la":-8.194,"de":17.5,"mw":5.6,"yr":2016,"ft":"T","s1":234,"d1":83,"r1":77,"s2":116,"d2":14,"r2":151,"label":""},{"lo":125.148,"la":4.725,"de":11.5,"mw":5.5,"yr":2016,"ft":"S","s1":109,"d1":77,"r1":-162,"s2":15,"d2":73,"r2":-13,"label":""},{"lo":125.332,"la":5.276,"de":190.5,"mw":5.5,"yr":2016,"ft":"N","s1":328,"d1":83,"r1":-79,"s2":93,"d2":12,"r2":-143,"label":""},{"lo":125.758,"la":1.37,"de":80.5,"mw":5.8,"yr":2016,"ft":"T","s1":30,"d1":63,"r1":92,"s2":205,"d2":27,"r2":86,"label":""},{"lo":126.102,"la":2.387,"de":60.5,"mw":5.5,"yr":2016,"ft":"N","s1":47,"d1":55,"r1":-71,"s2":197,"d2":39,"r2":-114,"label":""},{"lo":126.651,"la":4.207,"de":35.5,"mw":5.9,"yr":2016,"ft":"T","s1":344,"d1":62,"r1":85,"s2":174,"d2":28,"r2":99,"label":""},{"lo":127.0,"la":2.013,"de":109.4,"mw":5.6,"yr":2016,"ft":"S","s1":219,"d1":73,"r1":153,"s2":318,"d2":64,"r2":19,"label":""},{"lo":127.229,"la":-3.873,"de":11.5,"mw":5.6,"yr":2016,"ft":"S","s1":63,"d1":83,"r1":20,"s2":330,"d2":70,"r2":173,"label":""},{"lo":127.449,"la":1.77,"de":140.5,"mw":5.8,"yr":2016,"ft":"S","s1":188,"d1":74,"r1":127,"s2":297,"d2":40,"r2":25,"label":""},{"lo":127.834,"la":4.505,"de":150.5,"mw":5.7,"yr":2016,"ft":"T","s1":173,"d1":76,"r1":80,"s2":30,"d2":17,"r2":126,"label":""},{"lo":128.124,"la":-7.459,"de":150.5,"mw":5.6,"yr":2016,"ft":"T","s1":114,"d1":48,"r1":91,"s2":292,"d2":42,"r2":88,"label":""},{"lo":128.392,"la":3.206,"de":40.5,"mw":5.5,"yr":2016,"ft":"S","s1":192,"d1":82,"r1":-30,"s2":286,"d2":60,"r2":-170,"label":""},{"lo":129.492,"la":-5.566,"de":300.5,"mw":5.7,"yr":2016,"ft":"S","s1":236,"d1":76,"r1":-138,"s2":134,"d2":50,"r2":-18,"label":""},{"lo":130.43,"la":-6.029,"de":140.5,"mw":5.5,"yr":2016,"ft":"S","s1":59,"d1":76,"r1":51,"s2":312,"d2":41,"r2":158,"label":""},{"lo":130.479,"la":-6.258,"de":110.5,"mw":5.5,"yr":2016,"ft":"T","s1":60,"d1":65,"r1":70,"s2":282,"d2":32,"r2":127,"label":""},{"lo":131.82,"la":-6.987,"de":19.5,"mw":5.7,"yr":2016,"ft":"S","s1":54,"d1":81,"r1":23,"s2":320,"d2":67,"r2":170,"label":""},{"lo":114.574,"la":-11.539,"de":30.5,"mw":5.5,"yr":2017,"ft":"N","s1":95,"d1":43,"r1":-80,"s2":262,"d2":47,"r2":-99,"label":""},{"lo":115.323,"la":-8.492,"de":110.5,"mw":5.6,"yr":2017,"ft":"T","s1":161,"d1":36,"r1":81,"s2":352,"d2":54,"r2":97,"label":""},{"lo":120.204,"la":0.31,"de":60.5,"mw":5.5,"yr":2017,"ft":"S","s1":279,"d1":72,"r1":13,"s2":185,"d2":77,"r2":162,"label":""},{"lo":120.58,"la":0.309,"de":90.5,"mw":5.5,"yr":2017,"ft":"T","s1":309,"d1":42,"r1":57,"s2":171,"d2":56,"r2":116,"label":""},{"lo":121.984,"la":0.41,"de":110.5,"mw":5.9,"yr":2017,"ft":"T","s1":34,"d1":39,"r1":58,"s2":253,"d2":58,"r2":113,"label":""},{"lo":122.118,"la":-2.79,"de":17.5,"mw":5.7,"yr":2017,"ft":"S","s1":118,"d1":46,"r1":-10,"s2":215,"d2":83,"r2":-135,"label":""},{"lo":123.668,"la":-0.63,"de":25.5,"mw":5.5,"yr":2017,"ft":"S","s1":139,"d1":54,"r1":28,"s2":32,"d2":68,"r2":140,"label":""},{"lo":125.077,"la":0.03,"de":45.5,"mw":5.7,"yr":2017,"ft":"T","s1":39,"d1":71,"r1":77,"s2":255,"d2":23,"r2":123,"label":""},{"lo":125.415,"la":6.115,"de":80.5,"mw":5.8,"yr":2017,"ft":"S","s1":134,"d1":66,"r1":-1,"s2":225,"d2":89,"r2":-156,"label":""},{"lo":126.085,"la":-3.558,"de":25.5,"mw":5.8,"yr":2017,"ft":"S","s1":168,"d1":65,"r1":176,"s2":260,"d2":86,"r2":25,"label":""},{"lo":126.792,"la":4.08,"de":30.5,"mw":5.7,"yr":2017,"ft":"S","s1":225,"d1":65,"r1":-167,"s2":130,"d2":78,"r2":-25,"label":""},{"lo":127.095,"la":5.707,"de":19.5,"mw":5.7,"yr":2017,"ft":"T","s1":152,"d1":24,"r1":56,"s2":8,"d2":71,"r2":104,"label":""},{"lo":127.201,"la":5.675,"de":23.5,"mw":5.8,"yr":2017,"ft":"T","s1":157,"d1":34,"r1":56,"s2":16,"d2":63,"r2":110,"label":""},{"lo":127.3,"la":5.728,"de":21.5,"mw":5.5,"yr":2017,"ft":"T","s1":154,"d1":35,"r1":57,"s2":12,"d2":61,"r2":111,"label":""},{"lo":127.668,"la":-3.769,"de":11.5,"mw":5.6,"yr":2017,"ft":"T","s1":261,"d1":33,"r1":36,"s2":140,"d2":71,"r2":118,"label":""},{"lo":127.721,"la":-3.826,"de":11.5,"mw":5.8,"yr":2017,"ft":"S","s1":297,"d1":45,"r1":115,"s2":84,"d2":50,"r2":68,"label":""},{"lo":127.769,"la":-3.819,"de":11.5,"mw":5.7,"yr":2017,"ft":"T","s1":298,"d1":30,"r1":102,"s2":104,"d2":61,"r2":83,"label":""},{"lo":128.049,"la":-6.258,"de":19.5,"mw":5.5,"yr":2017,"ft":"S","s1":139,"d1":74,"r1":-172,"s2":47,"d2":82,"r2":-16,"label":""},{"lo":128.148,"la":2.465,"de":11.5,"mw":5.8,"yr":2017,"ft":"S","s1":26,"d1":77,"r1":-12,"s2":119,"d2":79,"r2":-166,"label":""},{"lo":128.208,"la":2.827,"de":45.5,"mw":5.6,"yr":2017,"ft":"S","s1":253,"d1":78,"r1":-172,"s2":161,"d2":82,"r2":-12,"label":""},{"lo":128.498,"la":3.94,"de":13.5,"mw":5.6,"yr":2017,"ft":"N","s1":159,"d1":31,"r1":-64,"s2":309,"d2":63,"r2":-105,"label":""},{"lo":129.782,"la":-6.736,"de":180.5,"mw":5.5,"yr":2017,"ft":"S","s1":71,"d1":54,"r1":39,"s2":315,"d2":59,"r2":137,"label":""},{"lo":131.091,"la":-4.855,"de":50.5,"mw":5.5,"yr":2017,"ft":"S","s1":5,"d1":87,"r1":2,"s2":275,"d2":88,"r2":177,"label":""},{"lo":116.013,"la":-8.395,"de":30.5,"mw":5.5,"yr":2018,"ft":"T","s1":96,"d1":25,"r1":99,"s2":266,"d2":65,"r2":86,"label":""},{"lo":116.23,"la":-8.306,"de":25.5,"mw":5.9,"yr":2018,"ft":"T","s1":84,"d1":22,"r1":87,"s2":267,"d2":68,"r2":91,"label":""},{"lo":116.926,"la":-8.422,"de":11.5,"mw":5.5,"yr":2018,"ft":"T","s1":196,"d1":40,"r1":87,"s2":21,"d2":50,"r2":93,"label":""},{"lo":119.392,"la":-2.907,"de":17.5,"mw":5.5,"yr":2018,"ft":"S","s1":88,"d1":43,"r1":-41,"s2":210,"d2":63,"r2":-125,"label":""},{"lo":120.119,"la":-10.472,"de":25.5,"mw":5.7,"yr":2018,"ft":"S","s1":268,"d1":57,"r1":-4,"s2":0,"d2":87,"r2":-147,"label":""},{"lo":120.143,"la":-10.475,"de":19.5,"mw":5.9,"yr":2018,"ft":"T","s1":328,"d1":42,"r1":123,"s2":106,"d2":56,"r2":64,"label":""},{"lo":123.645,"la":-6.311,"de":670.5,"mw":5.5,"yr":2018,"ft":"N","s1":89,"d1":37,"r1":-30,"s2":204,"d2":73,"r2":-123,"label":""},{"lo":123.762,"la":6.87,"de":550.5,"mw":5.9,"yr":2018,"ft":"N","s1":239,"d1":36,"r1":-27,"s2":352,"d2":74,"r2":-123,"label":""},{"lo":124.136,"la":-10.631,"de":11.5,"mw":5.7,"yr":2018,"ft":"T","s1":249,"d1":33,"r1":60,"s2":104,"d2":62,"r2":108,"label":""},{"lo":125.133,"la":5.896,"de":100.5,"mw":5.7,"yr":2018,"ft":"N","s1":105,"d1":31,"r1":-111,"s2":310,"d2":62,"r2":-78,"label":""},{"lo":125.182,"la":-0.247,"de":30.5,"mw":5.5,"yr":2018,"ft":"T","s1":267,"d1":40,"r1":139,"s2":31,"d2":65,"r2":58,"label":""},{"lo":126.657,"la":4.587,"de":30.5,"mw":5.7,"yr":2018,"ft":"S","s1":177,"d1":51,"r1":51,"s2":48,"d2":53,"r2":127,"label":""},{"lo":126.723,"la":-4.997,"de":11.5,"mw":5.6,"yr":2018,"ft":"S","s1":59,"d1":71,"r1":-4,"s2":151,"d2":86,"r2":-161,"label":""},{"lo":126.847,"la":2.378,"de":30.5,"mw":5.5,"yr":2018,"ft":"T","s1":13,"d1":35,"r1":95,"s2":188,"d2":55,"r2":87,"label":""},{"lo":127.981,"la":3.059,"de":60.5,"mw":5.5,"yr":2018,"ft":"S","s1":69,"d1":47,"r1":163,"s2":170,"d2":78,"r2":44,"label":""},{"lo":128.271,"la":-6.516,"de":370.5,"mw":5.6,"yr":2018,"ft":"N","s1":97,"d1":11,"r1":-40,"s2":227,"d2":83,"r2":-99,"label":""},{"lo":128.485,"la":-7.305,"de":150.5,"mw":5.7,"yr":2018,"ft":"T","s1":357,"d1":41,"r1":98,"s2":166,"d2":49,"r2":83,"label":""},{"lo":128.748,"la":-7.362,"de":140.5,"mw":5.5,"yr":2018,"ft":"T","s1":322,"d1":40,"r1":120,"s2":106,"d2":56,"r2":68,"label":""},{"lo":130.278,"la":-6.135,"de":150.5,"mw":5.9,"yr":2018,"ft":"S","s1":92,"d1":44,"r1":18,"s2":349,"d2":78,"r2":133,"label":""},{"lo":130.934,"la":-3.343,"de":17.5,"mw":5.6,"yr":2018,"ft":"T","s1":161,"d1":30,"r1":110,"s2":317,"d2":62,"r2":78,"label":""},{"lo":131.303,"la":-3.522,"de":13.5,"mw":5.5,"yr":2018,"ft":"T","s1":329,"d1":44,"r1":108,"s2":125,"d2":48,"r2":73,"label":""},{"lo":114.487,"la":-8.821,"de":90.5,"mw":5.7,"yr":2019,"ft":"T","s1":166,"d1":26,"r1":140,"s2":293,"d2":73,"r2":69,"label":""},{"lo":116.521,"la":-8.418,"de":25.5,"mw":5.6,"yr":2019,"ft":"N","s1":117,"d1":24,"r1":-66,"s2":271,"d2":69,"r2":-100,"label":""},{"lo":118.923,"la":-10.298,"de":21.5,"mw":5.6,"yr":2019,"ft":"T","s1":290,"d1":31,"r1":116,"s2":79,"d2":62,"r2":75,"label":""},{"lo":120.524,"la":-1.87,"de":15.5,"mw":5.5,"yr":2019,"ft":"T","s1":353,"d1":37,"r1":112,"s2":146,"d2":56,"r2":74,"label":""},{"lo":123.661,"la":1.985,"de":350.5,"mw":5.7,"yr":2019,"ft":"S","s1":297,"d1":61,"r1":-11,"s2":33,"d2":80,"r2":-151,"label":""},{"lo":124.168,"la":6.476,"de":480.5,"mw":5.5,"yr":2019,"ft":"N","s1":136,"d1":11,"r1":-161,"s2":27,"d2":87,"r2":-80,"label":""},{"lo":124.201,"la":1.185,"de":260.5,"mw":5.6,"yr":2019,"ft":"T","s1":151,"d1":32,"r1":2,"s2":59,"d2":89,"r2":121,"label":""},{"lo":124.985,"la":6.866,"de":23.5,"mw":5.9,"yr":2019,"ft":"S","s1":111,"d1":84,"r1":-3,"s2":202,"d2":87,"r2":-174,"label":""},{"lo":125.119,"la":6.814,"de":17.5,"mw":5.6,"yr":2019,"ft":"S","s1":325,"d1":84,"r1":1,"s2":235,"d2":89,"r2":174,"label":""},{"lo":125.26,"la":6.534,"de":15.5,"mw":5.6,"yr":2019,"ft":"S","s1":233,"d1":76,"r1":180,"s2":323,"d2":90,"r2":14,"label":""},{"lo":125.372,"la":6.252,"de":90.5,"mw":5.5,"yr":2019,"ft":"S","s1":242,"d1":58,"r1":-179,"s2":151,"d2":89,"r2":-32,"label":""},{"lo":126.19,"la":0.763,"de":30.5,"mw":5.5,"yr":2019,"ft":"S","s1":349,"d1":52,"r1":26,"s2":242,"d2":70,"r2":139,"label":""},{"lo":126.251,"la":0.449,"de":11.5,"mw":5.6,"yr":2019,"ft":"S","s1":349,"d1":60,"r1":5,"s2":256,"d2":85,"r2":150,"label":""},{"lo":126.304,"la":0.504,"de":19.5,"mw":5.9,"yr":2019,"ft":"T","s1":189,"d1":38,"r1":104,"s2":351,"d2":54,"r2":79,"label":""},{"lo":126.331,"la":1.582,"de":23.5,"mw":5.5,"yr":2019,"ft":"S","s1":203,"d1":46,"r1":109,"s2":357,"d2":47,"r2":71,"label":""},{"lo":126.335,"la":1.567,"de":30.5,"mw":5.9,"yr":2019,"ft":"T","s1":5,"d1":41,"r1":78,"s2":200,"d2":50,"r2":100,"label":""},{"lo":126.347,"la":1.616,"de":30.5,"mw":5.9,"yr":2019,"ft":"T","s1":20,"d1":42,"r1":79,"s2":215,"d2":49,"r2":100,"label":""},{"lo":126.417,"la":6.637,"de":50.5,"mw":5.7,"yr":2019,"ft":"S","s1":291,"d1":44,"r1":-138,"s2":168,"d2":62,"r2":-54,"label":""},{"lo":126.42,"la":1.467,"de":40.5,"mw":5.7,"yr":2019,"ft":"S","s1":24,"d1":45,"r1":92,"s2":202,"d2":45,"r2":88,"label":""},{"lo":126.453,"la":5.409,"de":30.5,"mw":5.6,"yr":2019,"ft":"T","s1":176,"d1":24,"r1":74,"s2":14,"d2":67,"r2":97,"label":""},{"lo":126.682,"la":4.03,"de":35.5,"mw":5.6,"yr":2019,"ft":"T","s1":175,"d1":35,"r1":96,"s2":347,"d2":56,"r2":86,"label":""},{"lo":126.754,"la":5.381,"de":45.5,"mw":5.6,"yr":2019,"ft":"S","s1":20,"d1":49,"r1":50,"s2":253,"d2":55,"r2":127,"label":""},{"lo":126.898,"la":5.811,"de":60.5,"mw":5.7,"yr":2019,"ft":"T","s1":19,"d1":34,"r1":122,"s2":162,"d2":62,"r2":71,"label":""},{"lo":126.986,"la":3.214,"de":17.5,"mw":5.6,"yr":2019,"ft":"T","s1":199,"d1":21,"r1":117,"s2":350,"d2":72,"r2":80,"label":""},{"lo":127.721,"la":-0.804,"de":19.5,"mw":5.8,"yr":2019,"ft":"S","s1":44,"d1":45,"r1":-60,"s2":185,"d2":52,"r2":-117,"label":""},{"lo":127.848,"la":-0.477,"de":11.5,"mw":5.8,"yr":2019,"ft":"N","s1":28,"d1":35,"r1":-99,"s2":219,"d2":55,"r2":-84,"label":""},{"lo":128.416,"la":-3.627,"de":23.5,"mw":5.5,"yr":2019,"ft":"N","s1":229,"d1":43,"r1":-58,"s2":8,"d2":55,"r2":-117,"label":""},{"lo":128.537,"la":-0.981,"de":11.5,"mw":5.8,"yr":2019,"ft":"T","s1":310,"d1":38,"r1":83,"s2":138,"d2":53,"r2":95,"label":""},{"lo":128.634,"la":3.483,"de":15.5,"mw":5.5,"yr":2019,"ft":"T","s1":321,"d1":33,"r1":17,"s2":217,"d2":81,"r2":122,"label":""},{"lo":130.407,"la":-6.518,"de":130.5,"mw":5.6,"yr":2019,"ft":"N","s1":42,"d1":31,"r1":-35,"s2":163,"d2":72,"r2":-117,"label":""},{"lo":130.426,"la":-6.458,"de":70.5,"mw":5.9,"yr":2019,"ft":"S","s1":313,"d1":47,"r1":118,"s2":96,"d2":49,"r2":63,"label":""},{"lo":130.725,"la":-5.843,"de":130.5,"mw":5.7,"yr":2019,"ft":"S","s1":110,"d1":50,"r1":38,"s2":353,"d2":62,"r2":133,"label":""},{"lo":131.856,"la":-6.576,"de":50.5,"mw":5.5,"yr":2019,"ft":"S","s1":254,"d1":69,"r1":14,"s2":159,"d2":76,"r2":159,"label":""},{"lo":116.928,"la":-7.006,"de":640.5,"mw":5.7,"yr":2020,"ft":"N","s1":289,"d1":20,"r1":-36,"s2":53,"d2":78,"r2":-107,"label":""},{"lo":120.177,"la":-1.714,"de":19.5,"mw":5.9,"yr":2020,"ft":"S","s1":35,"d1":73,"r1":-168,"s2":301,"d2":78,"r2":-17,"label":""},{"lo":120.456,"la":-7.202,"de":610.5,"mw":5.7,"yr":2020,"ft":"N","s1":16,"d1":21,"r1":-129,"s2":238,"d2":74,"r2":-76,"label":""},{"lo":124.086,"la":-10.373,"de":19.5,"mw":5.7,"yr":2020,"ft":"T","s1":240,"d1":40,"r1":58,"s2":99,"d2":57,"r2":114,"label":""},{"lo":124.976,"la":-5.753,"de":11.5,"mw":5.6,"yr":2020,"ft":"S","s1":127,"d1":48,"r1":172,"s2":223,"d2":84,"r2":42,"label":""},{"lo":125.702,"la":-7.935,"de":25.5,"mw":5.5,"yr":2020,"ft":"S","s1":105,"d1":71,"r1":178,"s2":196,"d2":88,"r2":19,"label":""},{"lo":125.758,"la":3.795,"de":130.5,"mw":5.5,"yr":2020,"ft":"T","s1":218,"d1":13,"r1":139,"s2":349,"d2":82,"r2":80,"label":""},{"lo":126.329,"la":0.714,"de":35.5,"mw":5.8,"yr":2020,"ft":"T","s1":11,"d1":36,"r1":75,"s2":209,"d2":56,"r2":100,"label":""},{"lo":126.344,"la":-4.224,"de":23.5,"mw":5.7,"yr":2020,"ft":"S","s1":158,"d1":82,"r1":174,"s2":248,"d2":84,"r2":8,"label":""},{"lo":126.52,"la":4.071,"de":30.5,"mw":5.6,"yr":2020,"ft":"T","s1":203,"d1":25,"r1":90,"s2":23,"d2":65,"r2":90,"label":""},{"lo":126.562,"la":1.669,"de":30.5,"mw":5.9,"yr":2020,"ft":"T","s1":22,"d1":28,"r1":83,"s2":210,"d2":62,"r2":94,"label":""},{"lo":126.645,"la":4.177,"de":23.5,"mw":5.7,"yr":2020,"ft":"T","s1":202,"d1":44,"r1":100,"s2":9,"d2":47,"r2":80,"label":""},{"lo":126.677,"la":1.107,"de":40.5,"mw":5.7,"yr":2020,"ft":"S","s1":156,"d1":83,"r1":3,"s2":66,"d2":87,"r2":173,"label":""},{"lo":129.241,"la":-7.072,"de":190.5,"mw":5.7,"yr":2020,"ft":"T","s1":267,"d1":40,"r1":135,"s2":35,"d2":63,"r2":60,"label":""},{"lo":129.366,"la":-6.76,"de":200.5,"mw":5.5,"yr":2020,"ft":"S","s1":196,"d1":46,"r1":-1,"s2":287,"d2":89,"r2":-136,"label":""},{"lo":129.755,"la":-4.871,"de":190.5,"mw":5.9,"yr":2020,"ft":"T","s1":88,"d1":9,"r1":6,"s2":352,"d2":89,"r2":98,"label":""},{"lo":129.911,"la":-6.061,"de":23.5,"mw":5.7,"yr":2020,"ft":"S","s1":43,"d1":78,"r1":6,"s2":312,"d2":84,"r2":167,"label":""},{"lo":129.935,"la":-2.877,"de":19.5,"mw":5.6,"yr":2020,"ft":"T","s1":166,"d1":37,"r1":145,"s2":285,"d2":70,"r2":58,"label":""},{"lo":131.484,"la":-3.346,"de":25.5,"mw":5.6,"yr":2020,"ft":"N","s1":292,"d1":37,"r1":-103,"s2":129,"d2":54,"r2":-80,"label":""},{"lo":118.894,"la":-2.981,"de":23.5,"mw":5.7,"yr":2021,"ft":"T","s1":359,"d1":37,"r1":74,"s2":199,"d2":55,"r2":102,"label":""},{"lo":120.433,"la":-7.253,"de":620.5,"mw":5.6,"yr":2021,"ft":"N","s1":233,"d1":26,"r1":-84,"s2":46,"d2":64,"r2":-93,"label":""},{"lo":121.53,"la":-0.839,"de":9.0,"mw":5.7,"yr":2021,"ft":"S","s1":133,"d1":77,"r1":19,"s2":39,"d2":72,"r2":167,"label":""},{"lo":121.905,"la":-0.673,"de":15.5,"mw":5.8,"yr":2021,"ft":"N","s1":132,"d1":29,"r1":-67,"s2":286,"d2":64,"r2":-102,"label":""},{"lo":121.91,"la":1.358,"de":21.5,"mw":5.8,"yr":2021,"ft":"T","s1":108,"d1":25,"r1":104,"s2":272,"d2":65,"r2":83,"label":""},{"lo":123.663,"la":0.141,"de":120.5,"mw":5.6,"yr":2021,"ft":"T","s1":348,"d1":39,"r1":146,"s2":106,"d2":70,"r2":57,"label":""},{"lo":124.298,"la":0.052,"de":50.5,"mw":5.6,"yr":2021,"ft":"T","s1":246,"d1":40,"r1":116,"s2":34,"d2":55,"r2":70,"label":""},{"lo":125.029,"la":5.671,"de":35.5,"mw":5.6,"yr":2021,"ft":"T","s1":35,"d1":41,"r1":130,"s2":167,"d2":60,"r2":61,"label":""},{"lo":125.25,"la":-0.08,"de":35.5,"mw":5.5,"yr":2021,"ft":"T","s1":258,"d1":40,"r1":125,"s2":35,"d2":59,"r2":64,"label":""},{"lo":125.459,"la":-7.709,"de":17.5,"mw":5.5,"yr":2021,"ft":"T","s1":38,"d1":24,"r1":37,"s2":273,"d2":76,"r2":110,"label":""},{"lo":126.156,"la":1.237,"de":35.5,"mw":5.5,"yr":2021,"ft":"T","s1":5,"d1":42,"r1":96,"s2":177,"d2":48,"r2":85,"label":""},{"lo":126.204,"la":0.807,"de":35.5,"mw":5.7,"yr":2021,"ft":"T","s1":207,"d1":41,"r1":108,"s2":4,"d2":51,"r2":75,"label":""},{"lo":127.106,"la":5.688,"de":45.5,"mw":5.7,"yr":2021,"ft":"S","s1":197,"d1":85,"r1":-176,"s2":107,"d2":86,"r2":-5,"label":""},{"lo":127.303,"la":6.292,"de":11.5,"mw":5.7,"yr":2021,"ft":"T","s1":144,"d1":15,"r1":42,"s2":13,"d2":80,"r2":101,"label":""},{"lo":127.526,"la":4.954,"de":110.5,"mw":5.5,"yr":2021,"ft":"T","s1":27,"d1":22,"r1":98,"s2":198,"d2":68,"r2":87,"label":""},{"lo":128.156,"la":-5.125,"de":350.5,"mw":5.9,"yr":2021,"ft":"T","s1":262,"d1":19,"r1":170,"s2":1,"d2":87,"r2":71,"label":""},{"lo":128.28,"la":-5.958,"de":360.5,"mw":5.7,"yr":2021,"ft":"T","s1":92,"d1":38,"r1":79,"s2":286,"d2":53,"r2":99,"label":""},{"lo":128.642,"la":3.958,"de":35.5,"mw":5.5,"yr":2021,"ft":"T","s1":206,"d1":42,"r1":108,"s2":3,"d2":51,"r2":75,"label":""},{"lo":128.685,"la":-7.044,"de":11.5,"mw":5.6,"yr":2021,"ft":"N","s1":37,"d1":29,"r1":-33,"s2":156,"d2":75,"r2":-115,"label":""},{"lo":129.339,"la":-2.947,"de":25.5,"mw":5.7,"yr":2021,"ft":"T","s1":139,"d1":38,"r1":122,"s2":281,"d2":59,"r2":68,"label":""},{"lo":129.524,"la":-3.558,"de":17.5,"mw":5.9,"yr":2021,"ft":"N","s1":27,"d1":34,"r1":-98,"s2":217,"d2":57,"r2":-85,"label":""},{"lo":130.497,"la":-6.88,"de":100.5,"mw":5.9,"yr":2021,"ft":"S","s1":90,"d1":72,"r1":16,"s2":355,"d2":75,"r2":162,"label":""},{"lo":118.539,"la":-2.769,"de":23.5,"mw":5.8,"yr":2022,"ft":"S","s1":324,"d1":42,"r1":10,"s2":227,"d2":84,"r2":132,"label":""},{"lo":120.433,"la":-7.322,"de":500.5,"mw":5.6,"yr":2022,"ft":"N","s1":115,"d1":43,"r1":-68,"s2":266,"d2":51,"r2":-109,"label":""},{"lo":120.621,"la":-8.207,"de":19.5,"mw":5.7,"yr":2022,"ft":"T","s1":100,"d1":26,"r1":99,"s2":271,"d2":64,"r2":86,"label":""},{"lo":120.791,"la":-8.09,"de":17.5,"mw":5.5,"yr":2022,"ft":"T","s1":96,"d1":23,"r1":95,"s2":270,"d2":67,"r2":88,"label":""},{"lo":123.664,"la":0.149,"de":130.5,"mw":5.6,"yr":2022,"ft":"T","s1":202,"d1":13,"r1":63,"s2":50,"d2":78,"r2":96,"label":""},{"lo":123.766,"la":6.833,"de":35.5,"mw":5.5,"yr":2022,"ft":"T","s1":359,"d1":27,"r1":96,"s2":172,"d2":63,"r2":87,"label":""},{"lo":123.792,"la":6.906,"de":35.5,"mw":5.8,"yr":2022,"ft":"S","s1":326,"d1":50,"r1":48,"s2":200,"d2":55,"r2":128,"label":""},{"lo":124.372,"la":0.357,"de":170.5,"mw":5.5,"yr":2022,"ft":"N","s1":145,"d1":31,"r1":-29,"s2":261,"d2":75,"r2":-118,"label":""},{"lo":124.664,"la":2.587,"de":250.5,"mw":5.6,"yr":2022,"ft":"N","s1":111,"d1":28,"r1":-151,"s2":356,"d2":77,"r2":-65,"label":""},{"lo":125.135,"la":6.733,"de":35.5,"mw":5.5,"yr":2022,"ft":"S","s1":59,"d1":87,"r1":177,"s2":149,"d2":87,"r2":3,"label":""},{"lo":125.466,"la":-7.002,"de":490.5,"mw":5.5,"yr":2022,"ft":"S","s1":212,"d1":50,"r1":-137,"s2":91,"d2":58,"r2":-49,"label":""},{"lo":126.176,"la":6.447,"de":50.5,"mw":5.6,"yr":2022,"ft":"S","s1":244,"d1":42,"r1":-161,"s2":140,"d2":78,"r2":-50,"label":""},{"lo":126.263,"la":0.931,"de":35.5,"mw":5.7,"yr":2022,"ft":"T","s1":342,"d1":40,"r1":71,"s2":187,"d2":52,"r2":106,"label":""},{"lo":126.386,"la":1.797,"de":30.5,"mw":5.7,"yr":2022,"ft":"T","s1":61,"d1":36,"r1":96,"s2":234,"d2":54,"r2":86,"label":""},{"lo":126.645,"la":6.007,"de":60.5,"mw":5.5,"yr":2022,"ft":"S","s1":278,"d1":56,"r1":155,"s2":22,"d2":69,"r2":36,"label":""},{"lo":126.871,"la":1.936,"de":30.5,"mw":5.9,"yr":2022,"ft":"T","s1":11,"d1":33,"r1":86,"s2":196,"d2":57,"r2":93,"label":""},{"lo":127.056,"la":6.488,"de":19.5,"mw":5.6,"yr":2022,"ft":"T","s1":191,"d1":33,"r1":88,"s2":13,"d2":57,"r2":91,"label":""},{"lo":127.202,"la":1.844,"de":35.5,"mw":5.6,"yr":2022,"ft":"S","s1":148,"d1":46,"r1":-65,"s2":294,"d2":49,"r2":-114,"label":""},{"lo":127.609,"la":6.152,"de":25.5,"mw":5.7,"yr":2022,"ft":"S","s1":171,"d1":45,"r1":-81,"s2":338,"d2":46,"r2":-98,"label":""},{"lo":129.954,"la":-6.723,"de":160.5,"mw":5.6,"yr":2022,"ft":"T","s1":261,"d1":12,"r1":144,"s2":26,"d2":83,"r2":80,"label":""},{"lo":118.679,"la":-7.811,"de":30.5,"mw":5.6,"yr":2023,"ft":"S","s1":65,"d1":73,"r1":12,"s2":331,"d2":78,"r2":163,"label":""},{"lo":121.446,"la":-8.379,"de":170.5,"mw":5.5,"yr":2023,"ft":"N","s1":5,"d1":29,"r1":-133,"s2":231,"d2":69,"r2":-70,"label":""},{"lo":123.924,"la":-9.043,"de":70.5,"mw":5.6,"yr":2023,"ft":"N","s1":26,"d1":37,"r1":-90,"s2":206,"d2":53,"r2":-90,"label":""},{"lo":124.148,"la":2.0,"de":310.5,"mw":5.8,"yr":2023,"ft":"S","s1":149,"d1":71,"r1":-4,"s2":240,"d2":86,"r2":-161,"label":""},{"lo":124.954,"la":-0.208,"de":23.5,"mw":5.6,"yr":2023,"ft":"T","s1":229,"d1":36,"r1":129,"s2":5,"d2":63,"r2":66,"label":""},{"lo":125.637,"la":-5.349,"de":15.5,"mw":5.5,"yr":2023,"ft":"S","s1":52,"d1":71,"r1":-12,"s2":146,"d2":78,"r2":-161,"label":""},{"lo":125.894,"la":-7.63,"de":19.5,"mw":5.5,"yr":2023,"ft":"T","s1":105,"d1":30,"r1":112,"s2":260,"d2":62,"r2":78,"label":""},{"lo":126.472,"la":-1.539,"de":11.5,"mw":5.6,"yr":2023,"ft":"S","s1":9,"d1":53,"r1":-33,"s2":120,"d2":64,"r2":-139,"label":""},{"lo":126.692,"la":3.589,"de":25.5,"mw":5.9,"yr":2023,"ft":"T","s1":201,"d1":24,"r1":99,"s2":11,"d2":66,"r2":86,"label":""},{"lo":126.944,"la":2.818,"de":30.5,"mw":5.8,"yr":2023,"ft":"T","s1":36,"d1":35,"r1":113,"s2":188,"d2":58,"r2":74,"label":""},{"lo":126.986,"la":2.839,"de":23.5,"mw":5.7,"yr":2023,"ft":"T","s1":18,"d1":38,"r1":95,"s2":192,"d2":52,"r2":86,"label":""},{"lo":127.05,"la":2.765,"de":25.5,"mw":5.9,"yr":2023,"ft":"S","s1":298,"d1":60,"r1":-16,"s2":37,"d2":76,"r2":-149,"label":""},{"lo":127.505,"la":4.711,"de":120.5,"mw":5.9,"yr":2023,"ft":"T","s1":46,"d1":34,"r1":129,"s2":182,"d2":64,"r2":67,"label":""},{"lo":129.224,"la":-7.15,"de":170.5,"mw":5.5,"yr":2023,"ft":"T","s1":239,"d1":21,"r1":99,"s2":49,"d2":69,"r2":87,"label":""},{"lo":129.506,"la":-7.026,"de":120.5,"mw":5.6,"yr":2023,"ft":"S","s1":77,"d1":40,"r1":20,"s2":331,"d2":78,"r2":128,"label":""},{"lo":129.688,"la":-7.035,"de":110.5,"mw":5.5,"yr":2023,"ft":"S","s1":78,"d1":44,"r1":41,"s2":316,"d2":63,"r2":126,"label":""},{"lo":129.728,"la":-7.062,"de":170.5,"mw":5.8,"yr":2023,"ft":"S","s1":314,"d1":51,"r1":179,"s2":45,"d2":89,"r2":39,"label":""},{"lo":129.946,"la":-5.558,"de":230.5,"mw":5.9,"yr":2023,"ft":"N","s1":272,"d1":20,"r1":-161,"s2":164,"d2":83,"r2":-71,"label":""},{"lo":130.133,"la":-6.148,"de":19.5,"mw":5.6,"yr":2023,"ft":"S","s1":58,"d1":78,"r1":10,"s2":325,"d2":80,"r2":168,"label":""},{"lo":130.156,"la":-5.707,"de":19.5,"mw":5.7,"yr":2023,"ft":"S","s1":53,"d1":44,"r1":-3,"s2":145,"d2":88,"r2":-134,"label":""},{"lo":130.219,"la":-6.02,"de":19.5,"mw":5.9,"yr":2023,"ft":"S","s1":328,"d1":76,"r1":-171,"s2":236,"d2":81,"r2":-14,"label":""},{"lo":118.481,"la":1.343,"de":11.5,"mw":5.5,"yr":2024,"ft":"T","s1":77,"d1":27,"r1":96,"s2":250,"d2":63,"r2":87,"label":""},{"lo":121.167,"la":-8.207,"de":23.5,"mw":5.6,"yr":2024,"ft":"T","s1":108,"d1":36,"r1":107,"s2":268,"d2":56,"r2":78,"label":""},{"lo":121.174,"la":1.504,"de":25.5,"mw":5.5,"yr":2024,"ft":"T","s1":145,"d1":23,"r1":106,"s2":307,"d2":68,"r2":83,"label":""},{"lo":122.183,"la":-9.421,"de":80.5,"mw":5.7,"yr":2024,"ft":"S","s1":163,"d1":69,"r1":30,"s2":62,"d2":62,"r2":157,"label":""},{"lo":122.913,"la":3.838,"de":530.5,"mw":5.5,"yr":2024,"ft":"N","s1":18,"d1":78,"r1":-106,"s2":251,"d2":20,"r2":-38,"label":""},{"lo":125.246,"la":-0.146,"de":25.5,"mw":5.7,"yr":2024,"ft":"T","s1":38,"d1":68,"r1":75,"s2":254,"d2":26,"r2":123,"label":""},{"lo":126.454,"la":4.376,"de":35.5,"mw":5.8,"yr":2024,"ft":"T","s1":0,"d1":81,"r1":76,"s2":238,"d2":16,"r2":146,"label":""},{"lo":127.267,"la":3.184,"de":35.5,"mw":5.6,"yr":2024,"ft":"S","s1":53,"d1":40,"r1":-1,"s2":144,"d2":89,"r2":-130,"label":""},{"lo":127.325,"la":-1.177,"de":11.5,"mw":5.6,"yr":2024,"ft":"S","s1":63,"d1":56,"r1":-34,"s2":174,"d2":62,"r2":-141,"label":""},{"lo":127.453,"la":-1.177,"de":11.5,"mw":5.8,"yr":2024,"ft":"N","s1":244,"d1":65,"r1":-71,"s2":24,"d2":31,"r2":-126,"label":""},{"lo":128.681,"la":-7.369,"de":150.5,"mw":5.5,"yr":2024,"ft":"T","s1":145,"d1":36,"r1":82,"s2":335,"d2":54,"r2":96,"label":""},{"lo":129.304,"la":-3.83,"de":17.5,"mw":5.5,"yr":2024,"ft":"T","s1":77,"d1":69,"r1":56,"s2":318,"d2":39,"r2":145,"label":""},{"lo":129.446,"la":-7.157,"de":90.5,"mw":5.8,"yr":2024,"ft":"S","s1":83,"d1":50,"r1":11,"s2":347,"d2":82,"r2":140,"label":""},{"lo":130.936,"la":-3.305,"de":15.5,"mw":5.5,"yr":2024,"ft":"T","s1":147,"d1":26,"r1":116,"s2":299,"d2":67,"r2":78,"label":""},{"lo":119.049,"la":-10.007,"de":25.5,"mw":5.6,"yr":2025,"ft":"N","s1":275,"d1":78,"r1":-97,"s2":128,"d2":14,"r2":-58,"label":""},{"lo":119.192,"la":-10.12,"de":25.5,"mw":5.6,"yr":2025,"ft":"T","s1":92,"d1":67,"r1":88,"s2":276,"d2":23,"r2":94,"label":""},{"lo":120.721,"la":-1.275,"de":11.5,"mw":5.8,"yr":2025,"ft":"T","s1":186,"d1":27,"r1":98,"s2":357,"d2":64,"r2":86,"label":""},{"lo":120.757,"la":-1.976,"de":19.5,"mw":5.5,"yr":2025,"ft":"S","s1":129,"d1":85,"r1":34,"s2":36,"d2":56,"r2":174,"label":""},{"lo":121.636,"la":0.505,"de":110.5,"mw":5.9,"yr":2025,"ft":"T","s1":249,"d1":71,"r1":107,"s2":26,"d2":26,"r2":50,"label":""},{"lo":123.065,"la":-0.125,"de":100.5,"mw":5.9,"yr":2025,"ft":"T","s1":84,"d1":38,"r1":86,"s2":269,"d2":52,"r2":93,"label":""},{"lo":124.146,"la":5.833,"de":17.5,"mw":5.9,"yr":2025,"ft":"T","s1":157,"d1":66,"r1":99,"s2":317,"d2":25,"r2":72,"label":""},{"lo":124.236,"la":5.804,"de":13.5,"mw":5.6,"yr":2025,"ft":"T","s1":162,"d1":66,"r1":96,"s2":328,"d2":24,"r2":77,"label":""},{"lo":124.857,"la":0.35,"de":11.5,"mw":5.5,"yr":2025,"ft":"S","s1":24,"d1":72,"r1":15,"s2":289,"d2":76,"r2":161,"label":""},{"lo":126.133,"la":-7.136,"de":470.5,"mw":5.9,"yr":2025,"ft":"S","s1":60,"d1":53,"r1":26,"s2":314,"d2":70,"r2":140,"label":""},{"lo":126.392,"la":1.446,"de":50.5,"mw":5.5,"yr":2025,"ft":"T","s1":173,"d1":50,"r1":91,"s2":351,"d2":40,"r2":89,"label":""},{"lo":126.726,"la":2.132,"de":40.5,"mw":5.8,"yr":2025,"ft":"T","s1":27,"d1":29,"r1":95,"s2":200,"d2":61,"r2":87,"label":""},{"lo":126.873,"la":2.024,"de":80.5,"mw":5.8,"yr":2025,"ft":"S","s1":43,"d1":89,"r1":-129,"s2":311,"d2":39,"r2":-2,"label":""},{"lo":127.118,"la":1.617,"de":100.5,"mw":5.5,"yr":2025,"ft":"T","s1":216,"d1":86,"r1":112,"s2":317,"d2":23,"r2":11,"label":""},{"lo":127.131,"la":2.167,"de":11.5,"mw":5.5,"yr":2025,"ft":"T","s1":327,"d1":39,"r1":56,"s2":188,"d2":59,"r2":114,"label":""},{"lo":127.373,"la":6.999,"de":11.5,"mw":5.8,"yr":2025,"ft":"T","s1":5,"d1":70,"r1":91,"s2":182,"d2":20,"r2":87,"label":""},{"lo":128.225,"la":3.038,"de":120.5,"mw":5.9,"yr":2025,"ft":"S","s1":128,"d1":54,"r1":17,"s2":28,"d2":77,"r2":143,"label":""},{"lo":128.344,"la":-7.322,"de":160.5,"mw":5.6,"yr":2025,"ft":"T","s1":31,"d1":41,"r1":58,"s2":250,"d2":56,"r2":114,"label":""},{"lo":128.4,"la":-3.715,"de":110.5,"mw":5.8,"yr":2025,"ft":"N","s1":35,"d1":80,"r1":-119,"s2":287,"d2":30,"r2":-20,"label":""},{"lo":128.529,"la":-7.436,"de":140.5,"mw":5.7,"yr":2025,"ft":"S","s1":36,"d1":40,"r1":20,"s2":290,"d2":78,"r2":128,"label":""},{"lo":130.162,"la":-2.831,"de":17.5,"mw":5.8,"yr":2025,"ft":"T","s1":107,"d1":16,"r1":47,"s2":331,"d2":78,"r2":101,"label":""},{"lo":130.652,"la":-6.023,"de":150.5,"mw":5.6,"yr":2025,"ft":"T","s1":53,"d1":74,"r1":57,"s2":300,"d2":36,"r2":151,"label":""},{"lo":130.924,"la":-6.249,"de":90.5,"mw":5.6,"yr":2025,"ft":"S","s1":62,"d1":76,"r1":53,"s2":314,"d2":39,"r2":157,"label":""},{"lo":131.039,"la":-3.366,"de":11.5,"mw":5.7,"yr":2025,"ft":"T","s1":313,"d1":73,"r1":91,"s2":128,"d2":17,"r2":85,"label":""},{"lo":131.536,"la":-0.396,"de":15.5,"mw":5.6,"yr":2025,"ft":"S","s1":264,"d1":90,"r1":13,"s2":174,"d2":77,"r2":180,"label":""},{"lo":119.325,"la":-10.114,"de":23.5,"mw":5.8,"yr":2026,"ft":"T","s1":103,"d1":71,"r1":95,"s2":270,"d2":20,"r2":77,"label":""},{"lo":122.081,"la":1.377,"de":23.5,"mw":5.5,"yr":2026,"ft":"S","s1":355,"d1":53,"r1":10,"s2":258,"d2":82,"r2":143,"label":""},{"lo":123.741,"la":6.432,"de":11.5,"mw":5.9,"yr":2026,"ft":"T","s1":185,"d1":78,"r1":103,"s2":318,"d2":18,"r2":45,"label":""},{"lo":126.063,"la":1.058,"de":40.5,"mw":5.6,"yr":2026,"ft":"S","s1":199,"d1":55,"r1":122,"s2":331,"d2":46,"r2":53,"label":""},{"lo":126.355,"la":1.292,"de":11.5,"mw":5.9,"yr":2026,"ft":"T","s1":10,"d1":69,"r1":92,"s2":184,"d2":21,"r2":85,"label":""},{"lo":126.374,"la":0.849,"de":17.5,"mw":5.5,"yr":2026,"ft":"T","s1":16,"d1":28,"r1":72,"s2":216,"d2":64,"r2":99,"label":""},{"lo":126.432,"la":1.319,"de":11.5,"mw":5.6,"yr":2026,"ft":"T","s1":6,"d1":40,"r1":81,"s2":197,"d2":50,"r2":97,"label":""},{"lo":127.858,"la":-7.507,"de":170.5,"mw":5.8,"yr":2026,"ft":"T","s1":110,"d1":38,"r1":46,"s2":340,"d2":64,"r2":118,"label":""},{"lo":128.252,"la":4.157,"de":11.5,"mw":5.6,"yr":2026,"ft":"T","s1":169,"d1":17,"r1":79,"s2":1,"d2":73,"r2":93,"label":""},{"lo":130.151,"la":-7.689,"de":13.5,"mw":5.7,"yr":2026,"ft":"T","s1":52,"d1":26,"r1":103,"s2":217,"d2":64,"r2":83,"label":""}]